verilog/i2s_receive2/common_test_util.v
`timescale 1ns/1ns
module common_test_util
  (
   input clk
   );

  parameter check_width = 32;
  parameter msg_length = 80;
  parameter excessive_output_threshold = 100;
  parameter error_msg_prefix = "ERROR:";

  reg verbose;
  integer num_errors;
  event Error;
  task IncrErrorCount;
    begin
      num_errors=num_errors+1;
    end
  endtask

  integer num_checks;
  event Check;
  task IncrCheckCount;
    begin
      num_checks=num_checks+1;
    end
  endtask

  task init;
    begin
      num_checks = 0;
      num_errors = 0;
      verbose = $test$plusargs("verbose");
      $display("INFO: %m: Simulation start.");
    end
  endtask

  function [check_width-1:0] random;
    input nothing;
    reg [((check_width+31)/32)*32-1:0] r;
    integer i;
    begin
      for (i=0; i<=(check_width-1)/32; i=i+1)
	r[i*32+:32] = {$random};
      random = r;
    end
  endfunction

  task wrapup;
    begin
      $display("INFO: %m: Simulation complete at time %.2fns. %0d comparisons attempted.",$realtime,num_checks);

      if (num_errors == 0)
	$display("INFO: %m: Simulation PASSED with %0d comparisons",num_checks);
      else
	$display("INFO: %m: Simulation FAILS with %0d errors out of %0d comparisons",num_errors,num_checks);
    end
  endtask

  reg output_disable = 0;
  task check_output_limits;
    begin
      if (num_errors == excessive_output_threshold)
	begin
	  $display("INFO: %m: excessive error messages truncated after %0d errors.",num_errors);
	  output_disable = 1;
	end
    end
  endtask

  task check;
    input [check_width-1:0] value;
    input [check_width-1:0] expected;
    begin
      ->Check;
      IncrCheckCount;
      if (value !== expected)
	begin
	  ->Error;
	  IncrErrorCount;
	  if (!output_disable) $display("ERROR: %m: test value %x, expected %x at time %.2fns",value,expected,$realtime);
	  check_output_limits;
	end
    end
  endtask

  task msg_check;
    input [msg_length*8-1:0] msg;
    input [check_width-1:0] value;
    input [check_width-1:0] expected;
    reg [msg_length*2*8-1:0] buffer;
    reg [(msg_length+64)*8-1:0]  msg_str;
    begin
      ->Check;
      IncrCheckCount;
      if (value !== expected)
	begin
	  ->Error;
	  IncrErrorCount;
 	  // icarus complains that $sformat second arg must be a reg or string.
	  msg_str = {"ERROR: %m: ",msg," at time %.2fns"};
	  $sformat(buffer,msg_str,value,expected,$realtime);
	  if (!output_disable) $display("%0s",buffer);
	  check_output_limits;
	end
    end
  endtask

  function real abs;
    input real x;
    begin
      if (x<0)
	abs = -x;
      else
	abs = x;
    end
  endfunction

  task check_real;
    input real value;
    input real expected;
    input real precision;
    begin
      ->Check;
      IncrCheckCount;
      if (abs(value-expected) > precision)
	begin
	  ->Error;
	  IncrErrorCount;
	  if (!output_disable)
	    $display("ERROR: %m: measured %f, expected %f, delta=%f (precision=%f) at time %.2fns",
		     value,expected,value-expected,precision,$realtime);
	  check_output_limits;
	end
    end
  endtask

  task check_time;
    input time value;
    input time expected;
    begin
      ->Check;
      IncrCheckCount;
      if (value != expected)
	begin
	  ->Error;
	  IncrErrorCount;
	  if (!output_disable)
	    $display("ERROR: %m: measured %0tns, expected %0tns",value,expected);
	  check_output_limits;
	end
    end
  endtask

  event StartWatchDog;
  reg [31:0] watchdog_cycles;
  reg [80*8-1:0] watchdog_name;
  initial watchdog_name = "";
  always @(StartWatchDog)
    begin : watchdog_timer
      repeat (watchdog_cycles)
	@(posedge clk);
      $display("Watchdog timer %0s expired at %t",watchdog_name,$time);
      $finish;
    end
  
  task named_watchdog;
    input [31:0] cycles;
    input [80*8-1:0] name;
    begin
      watchdog_name = name;
      watchdog_cycles = cycles;
      ->StartWatchDog;
    end
  endtask

  task watchdog;
    input [31:0] cycles;
    begin
      watchdog_name = "";
      watchdog_cycles = cycles;
      ->StartWatchDog;
    end
  endtask

  task spin;
    input integer cycles;
    begin
      repeat (cycles) @(posedge clk);
    end
  endtask

endmodule

verilog/i2s_receive/i2s_receive.v
module i2s_receive (
    input  wire        rst,         // Active high reset
    input  wire        rx_en,      // Enable signal for receiving data
    input  wire        clk,         // System clock   
    input  wire        sck,         // I2S bit clock (BCLK)
    input  wire        ws,          // I2S word select (LRCLK)
    input  wire        sd,          // I2S serial data
    output reg  [31:0] data_left,   // Left channel data
    output reg  [31:0] data_right  // Right channel data
);

reg [31:0] shift_reg; // Shift register for I2S data
reg wsd; // Previous state of word select
reg wsdd; // Previous state of word select (for edge detection)
reg wsp; // Previous state of word select (for edge detection)
reg data_left_enable; // Enable signal for left channel data
reg data_right_enable; // Enable signal for right channel data

always @(posedge clk) begin
    if (rst) begin
        shift_reg <= 32'b0; // Reset shift register
        data_left <= 32'b0; // Reset left channel data
        data_right <= 32'b0; // Reset right channel data    
        wsd <= 1'b0; // Reset word select state
        wsdd <= 1'b0; // Reset last word select state 
        //data_left_enable <= 1'b0; // Disable left channel data      
        //data_right_enable <= 1'b0; // Disable right channel data
    end else if (rx_en && sck) begin // this only works when CLK is 2x sck
        shift_reg <= {shift_reg[30:0], sd}; // Shift in the serial data
        wsd <= ws; // Store the current state of word select
        wsdd <= wsd; // Store the last state of word select
        
        if (data_left_enable) begin
            data_left <= shift_reg; // Capture left channel data
        end else if (data_right_enable) begin
            data_right <= shift_reg; // Capture right channel data
        end
    end
end

always @(*) begin
    wsp <= wsdd ^ wsd; // Update previous state of word select for edge detection
    data_left_enable <= (wsd == 1'b1) && (wsp == 1'b1); // Enable left channel data on rising edge of WS
    data_right_enable <= (wsd == 1'b0) && (wsp == 1'b1); // Enable right channel data on rising edge of WS
end

endmodule

// module that checks for a full ws cycle before enabling the receiver
module rx_en_ws_check (
    input  wire clk,        // System clock
    input  wire rst,        // Active high reset
    input  wire ws,         // I2S word select (LRCLK)
    output wire rx_en       // Enable signal for receiving data
);

    reg state_fclk = 0;
    reg fclk_d;
    reg fclk_dd;
    reg [1:0] edge_cnt = 2'b00;

    wire fclk_falling = (!ws && fclk_dd);
    // monitor that a full fclk period has passed before allowing writes (so state_fclk turns high on 2nd positive edge)
    always @(posedge clk) begin
        if (rst) begin
            state_fclk <= 0;
            fclk_d <= 0;
            edge_cnt <= 2'b00;
        end else begin
            fclk_d <= ws;
            fclk_dd <= fclk_d;

            if (fclk_falling) begin
                if (edge_cnt < 2'd2)
                    edge_cnt <= edge_cnt + 1'b1;
                
                if (edge_cnt == 2'd1)
                    state_fclk <= 1; // Clear state on first fclk rising edge
            end
        end
    end

    assign rx_en = state_fclk; // Allow write if not full and state is set

endmodule

verilog/i2s_receive/i2s_receive_tb.v
`timescale 1ns/1ns
module i2s_receive_tb;

    reg sck;
    always #40 sck = (sck === 1'b0);  

    reg clk;
    always #20 clk = (clk === 1'b0);  
  
    reg ws;
    always #2560 ws = (ws === 1'b0);

    reg reset = 1;
    initial begin
        repeat(10) @(posedge sck);
        reset <= 0;
    end

    //reg ws = 1;
    reg sd;
    wire [31:0] data_left, data_right;

    wire rx_en_tb;

    i2s_receive dut (
        .sck(sck),
        .clk(clk),
        .rst(reset),
        .rx_en(rx_en_tb),
        .ws(ws),
        .sd(sd),
        .data_left(data_left),
        .data_right(data_right)
    );

    rx_en_ws_check rx_en_inst (
        .clk(clk),
        .rst(reset),
        .ws(ws),
        .rx_en(rx_en_tb)
    );

  
    reg [31:0] expected_left, expected_right, sent_left, sent_right;
    reg [0:63] shift_data;

    common_test_util #(32) util(sck);

    reg stimulus_complete=0;
    event check_left_output;
    event check_right_output;

    initial begin
        // VCD dump for waveform
        $dumpfile("i2s_receive_tb.vcd");
        $dumpvars(0, i2s_receive_tb);

        wait (!reset);
        sd <= 0;
        @(negedge ws);

        // first 2 words will be ignored so send zeroes
        @(negedge sck);

        shift_data = {{32{1'b0}}, {32{1'b0}}};
        sent_left = shift_data[0:31];
        sent_right = shift_data[32:63];
    
        repeat (31) begin
            sd <= shift_data[0];
            shift_data <= shift_data<<1;
            @(negedge sck);
        end

        expected_left = sent_left;
        ->check_left_output;
        
        //ws <= 1;
        repeat (32) begin
        sd <= shift_data[0];
        shift_data <= shift_data<<1;
        @(negedge sck);
        end
        
        expected_right = sent_right;
        ->check_right_output;
        
        sd <= shift_data[0];


        repeat (100) begin
            @(negedge sck);

            shift_data = {{$random}, {$random}};
            sent_left = shift_data[0:31];
            sent_right = shift_data[32:63];
        
            repeat (31) begin
                sd <= shift_data[0];
                shift_data <= shift_data<<1;
                @(negedge sck);
            end

            expected_left = sent_left;
            ->check_left_output;
            
            //ws <= 1;
            repeat (32) begin
            sd <= shift_data[0];
            shift_data <= shift_data<<1;
            @(negedge sck);
            end
            
            expected_right = sent_right;
            ->check_right_output;
            
            sd <= shift_data[0];
            //ws <= 0;
        end
        
        stimulus_complete = 1;
    end

    always @(check_left_output) begin
        repeat (2) @(negedge sck);
        util.check(data_left,expected_left);
    end

    always @(check_right_output) begin
        repeat (2) @(negedge sck);
        util.check(data_right,expected_right);
    end
    
    initial begin
        util.init();

        wait (stimulus_complete);

        repeat (10) @(negedge sck);
        util.wrapup();
        $finish;
    end

endmodule

verilog/i2s_receive/i2s_receive_tb.vcd
$date
	Fri Aug 29 13:29:44 2025
$end
$version
	Icarus Verilog
$end
$timescale
	1ps
$end
$scope module i2s_receive_tb $end
$var event 1 ! check_right_output $end
$var event 1 " check_left_output $end
$var wire 1 # rx_en_tb $end
$var wire 32 $ data_right [31:0] $end
$var wire 32 % data_left [31:0] $end
$var reg 1 & clk $end
$var reg 32 ' expected_left [31:0] $end
$var reg 32 ( expected_right [31:0] $end
$var reg 1 ) reset $end
$var reg 1 * sck $end
$var reg 1 + sd $end
$var reg 32 , sent_left [31:0] $end
$var reg 32 - sent_right [31:0] $end
$var reg 64 . shift_data [0:63] $end
$var reg 1 / stimulus_complete $end
$var reg 1 0 ws $end
$scope module dut $end
$var wire 1 & clk $end
$var wire 1 ) rst $end
$var wire 1 * sck $end
$var wire 1 + sd $end
$var wire 1 0 ws $end
$var wire 1 # rx_en $end
$var reg 32 1 data_left [31:0] $end
$var reg 1 2 data_left_enable $end
$var reg 32 3 data_right [31:0] $end
$var reg 1 4 data_right_enable $end
$var reg 32 5 shift_reg [31:0] $end
$var reg 1 6 wsd $end
$var reg 1 7 wsdd $end
$var reg 1 8 wsp $end
$upscope $end
$scope module rx_en_inst $end
$var wire 1 & clk $end
$var wire 1 9 fclk_falling $end
$var wire 1 ) rst $end
$var wire 1 # rx_en $end
$var wire 1 0 ws $end
$var reg 2 : edge_cnt [1:0] $end
$var reg 1 ; fclk_d $end
$var reg 1 < fclk_dd $end
$var reg 1 = state_fclk $end
$upscope $end
$scope module util $end
$var event 1 > StartWatchDog $end
$var event 1 ? Error $end
$var event 1 @ Check $end
$var wire 1 * clk $end
$var parameter 32 A check_width $end
$var parameter 48 B error_msg_prefix $end
$var parameter 32 C excessive_output_threshold $end
$var parameter 32 D msg_length $end
$var reg 1 E output_disable $end
$var reg 1 F verbose $end
$var reg 32 G watchdog_cycles [31:0] $end
$var reg 640 H watchdog_name [639:0] $end
$var integer 32 I num_checks [31:0] $end
$var integer 32 J num_errors [31:0] $end
$scope function abs $end
$var real 1 K x $end
$upscope $end
$scope function random $end
$var reg 1 L nothing $end
$var reg 32 M r [31:0] $end
$var integer 32 N i [31:0] $end
$upscope $end
$scope begin watchdog_timer $end
$upscope $end
$scope task IncrCheckCount $end
$upscope $end
$scope task IncrErrorCount $end
$upscope $end
$scope task check $end
$var reg 32 O expected [31:0] $end
$var reg 32 P value [31:0] $end
$upscope $end
$scope task check_output_limits $end
$upscope $end
$scope task check_real $end
$var real 1 Q expected $end
$var real 1 R precision $end
$var real 1 S value $end
$upscope $end
$scope task check_time $end
$var reg 64 T expected [63:0] $end
$var reg 64 U value [63:0] $end
$upscope $end
$scope task init $end
$upscope $end
$scope task msg_check $end
$var reg 1280 V buffer [1279:0] $end
$var reg 32 W expected [31:0] $end
$var reg 640 X msg [639:0] $end
$var reg 1152 Y msg_str [1151:0] $end
$var reg 32 Z value [31:0] $end
$upscope $end
$scope task named_watchdog $end
$var reg 32 [ cycles [31:0] $end
$var reg 640 \ name [639:0] $end
$upscope $end
$scope task spin $end
$var integer 32 ] cycles [31:0] $end
$upscope $end
$scope task watchdog $end
$var reg 32 ^ cycles [31:0] $end
$upscope $end
$scope task wrapup $end
$upscope $end
$upscope $end
$upscope $end
$enddefinitions $end
$comment Show the parameter values. $end
$dumpall
b1010000 D
b1100100 C
b10001010101001001010010010011110101001000111010 B
b100000 A
$end
#0
$dumpvars
bx ^
bx ]
bx \
bx [
bx Z
bx Y
bx X
bx W
bx V
bx U
bx T
r0 S
r0 R
r0 Q
bx P
bx O
bx N
bx M
xL
r0 K
b0 J
b0 I
b0 H
bx G
0F
0E
1@
1?
1>
0=
x<
x;
b0 :
x9
x8
x7
x6
bx 5
x4
bx 3
x2
bx 1
x0
0/
bx .
bx -
bx ,
x+
x*
1)
bx (
bx '
x&
bx %
bx $
0#
1"
1!
$end
#20000
0&
#40000
04
02
08
07
06
b0 $
b0 3
b0 %
b0 1
b0 5
0;
1&
0*
#60000
0&
#80000
1&
1*
#100000
0&
#120000
1&
0*
#140000
0&
#160000
1&
1*
#180000
0&
#200000
1&
0*
#220000
0&
#240000
1&
1*
#260000
0&
#280000
1&
0*
#300000
0&
#320000
1&
1*
#340000
0&
#360000
1&
0*
#380000
0&
#400000
1&
1*
#420000
0&
#440000
1&
0*
#460000
0&
#480000
1&
1*
#500000
0&
#520000
1&
0*
#540000
0&
#560000
1&
1*
#580000
0&
#600000
1&
0*
#620000
0&
#640000
1&
1*
#660000
0&
#680000
1&
0*
#700000
0&
#720000
1&
1*
#740000
0&
#760000
1&
0*
#780000
0&
#800000
0+
0)
1&
1*
#820000
0&
#840000
09
0<
x;
1&
0*
#860000
0&
#880000
x9
x<
1&
1*
#900000
0&
#920000
1&
0*
#940000
0&
#960000
1&
1*
#980000
0&
#1000000
1&
0*
#1020000
0&
#1040000
1&
1*
#1060000
0&
#1080000
1&
0*
#1100000
0&
#1120000
1&
1*
#1140000
0&
#1160000
1&
0*
#1180000
0&
#1200000
1&
1*
#1220000
0&
#1240000
1&
0*
#1260000
0&
#1280000
1&
1*
#1300000
0&
#1320000
1&
0*
#1340000
0&
#1360000
1&
1*
#1380000
0&
#1400000
1&
0*
#1420000
0&
#1440000
1&
1*
#1460000
0&
#1480000
1&
0*
#1500000
0&
#1520000
1&
1*
#1540000
0&
#1560000
1&
0*
#1580000
0&
#1600000
1&
1*
#1620000
0&
#1640000
1&
0*
#1660000
0&
#1680000
1&
1*
#1700000
0&
#1720000
1&
0*
#1740000
0&
#1760000
1&
1*
#1780000
0&
#1800000
1&
0*
#1820000
0&
#1840000
1&
1*
#1860000
0&
#1880000
1&
0*
#1900000
0&
#1920000
1&
1*
#1940000
0&
#1960000
1&
0*
#1980000
0&
#2000000
1&
1*
#2020000
0&
#2040000
1&
0*
#2060000
0&
#2080000
1&
1*
#2100000
0&
#2120000
1&
0*
#2140000
0&
#2160000
1&
1*
#2180000
0&
#2200000
1&
0*
#2220000
0&
#2240000
1&
1*
#2260000
0&
#2280000
1&
0*
#2300000
0&
#2320000
1&
1*
#2340000
0&
#2360000
1&
0*
#2380000
0&
#2400000
1&
1*
#2420000
0&
#2440000
1&
0*
#2460000
0&
#2480000
1&
1*
#2500000
0&
#2520000
1&
0*
#2540000
0&
#2560000
0;
1&
1*
00
#2580000
0&
#2600000
09
0<
b0 -
b0 ,
b0 .
1&
0*
#2620000
0&
#2640000
1&
1*
#2660000
0&
#2680000
1&
0*
#2700000
0&
#2720000
1&
1*
#2740000
0&
#2760000
1&
0*
#2780000
0&
#2800000
1&
1*
#2820000
0&
#2840000
1&
0*
#2860000
0&
#2880000
1&
1*
#2900000
0&
#2920000
1&
0*
#2940000
0&
#2960000
1&
1*
#2980000
0&
#3000000
1&
0*
#3020000
0&
#3040000
1&
1*
#3060000
0&
#3080000
1&
0*
#3100000
0&
#3120000
1&
1*
#3140000
0&
#3160000
1&
0*
#3180000
0&
#3200000
1&
1*
#3220000
0&
#3240000
1&
0*
#3260000
0&
#3280000
1&
1*
#3300000
0&
#3320000
1&
0*
#3340000
0&
#3360000
1&
1*
#3380000
0&
#3400000
1&
0*
#3420000
0&
#3440000
1&
1*
#3460000
0&
#3480000
1&
0*
#3500000
0&
#3520000
1&
1*
#3540000
0&
#3560000
1&
0*
#3580000
0&
#3600000
1&
1*
#3620000
0&
#3640000
1&
0*
#3660000
0&
#3680000
1&
1*
#3700000
0&
#3720000
1&
0*
#3740000
0&
#3760000
1&
1*
#3780000
0&
#3800000
1&
0*
#3820000
0&
#3840000
1&
1*
#3860000
0&
#3880000
1&
0*
#3900000
0&
#3920000
1&
1*
#3940000
0&
#3960000
1&
0*
#3980000
0&
#4000000
1&
1*
#4020000
0&
#4040000
1&
0*
#4060000
0&
#4080000
1&
1*
#4100000
0&
#4120000
1&
0*
#4140000
0&
#4160000
1&
1*
#4180000
0&
#4200000
1&
0*
#4220000
0&
#4240000
1&
1*
#4260000
0&
#4280000
1&
0*
#4300000
0&
#4320000
1&
1*
#4340000
0&
#4360000
1&
0*
#4380000
0&
#4400000
1&
1*
#4420000
0&
#4440000
1&
0*
#4460000
0&
#4480000
1&
1*
#4500000
0&
#4520000
1&
0*
#4540000
0&
#4560000
1&
1*
#4580000
0&
#4600000
1&
0*
#4620000
0&
#4640000
1&
1*
#4660000
0&
#4680000
1&
0*
#4700000
0&
#4720000
1&
1*
#4740000
0&
#4760000
1&
0*
#4780000
0&
#4800000
1&
1*
#4820000
0&
#4840000
1&
0*
#4860000
0&
#4880000
1&
1*
#4900000
0&
#4920000
1&
0*
#4940000
0&
#4960000
1&
1*
#4980000
0&
#5000000
1&
0*
#5020000
0&
#5040000
1&
1*
#5060000
0&
#5080000
1"
b0 '
1&
0*
#5100000
0&
#5120000
1;
1&
1*
10
#5140000
0&
#5160000
1<
1&
0*
#5180000
0&
#5200000
1&
1*
#5220000
0&
#5240000
b1 I
1@
b0 O
b0 P
1&
0*
