verilog/spdif_transmit2/spdif_transmit2.v
module spdif_transmit2 (
    input  wire        rst,
    input  wire        clk,                // bit_clock: 128x Fsample
    input  wire [31:0] data_left,          // 24 bits valid, left-justified
    input  wire [31:0] data_right,         // 24 bits valid, left-justified
    input  wire        validity,           // validity bit
    input  wire [3:0]  sample_rate_code,   // IEC60958 sample rate code
    output reg         spdif_out
);

    // Channel status word (24 bits used here, can be expanded to 192)
    reg [23:0] channel_status = 24'b001000000000000001000000;
    reg [23:0] channel_status_shift = 24'b001000000000000001000000;

    reg [23:0] data_in_buffer = 0;
    reg [5:0]  bit_counter = 0;
    reg [8:0]  frame_counter = 0;
    reg        parity = 0;
    reg [7:0]  data_out_buffer = 0;
    reg        data_biphase = 0;

    // Sample rate code assignment (bits 23:20 or as needed)
    always @(*) begin
        channel_status[23:20] = sample_rate_code;
    end

    // Bit counter
    always @(posedge clk) begin
        if (rst)
            bit_counter <= 0;
        else
            bit_counter <= bit_counter + 1;
    end

    // Data latch and frame counter
    always @(posedge clk) begin
        if (rst) begin
            data_in_buffer <= 0;
            frame_counter  <= 0;
            parity         <= 0;
        end else begin
            // Latch new sample every 4th bit (bit_counter == 3)
            if (bit_counter == 6'd3)
                data_in_buffer <= data_left[31:8]; // 24 MSBs

            // Parity calculation (XOR of all bits + channel status)
            parity <= ^data_in_buffer ^ channel_status_shift[23];

            // Frame counter update
            if (bit_counter == 6'd63) begin
                if (frame_counter == 9'd383)
                    frame_counter <= 0;
                else
                    frame_counter <= frame_counter + 1;
            end
        end
    end

    // Data output buffer
    always @(posedge clk) begin
        if (rst) begin
            data_out_buffer <= 0;
            channel_status_shift <= channel_status;
        end else begin
            if (bit_counter == 6'd63) begin
                // Load preamble and channel status for new frame
                if (frame_counter == 9'd383) begin
                    // Preamble Z
                    data_out_buffer <= 8'b10011100;
                    channel_status_shift <= channel_status;
                end else if (frame_counter[0] == 1'b1) begin
                    // Preamble X (even frame)
                    data_out_buffer <= 8'b10010011;
                    channel_status_shift <= {channel_status_shift[22:0], 1'b0};
                end else begin
                    // Preamble Y (odd frame)
                    data_out_buffer <= 8'b10010110;
                    // channel_status_shift unchanged
                end
            end else if (bit_counter[2:0] == 3'b111) begin
                case (bit_counter[5:3])
                    3'b000: data_out_buffer <= {1'b1, data_in_buffer[0], 1'b1, data_in_buffer[1], 1'b1, data_in_buffer[2], 1'b1, data_in_buffer[3]};
                    3'b001: data_out_buffer <= {1'b1, data_in_buffer[4], 1'b1, data_in_buffer[5], 1'b1, data_in_buffer[6], 1'b1, data_in_buffer[7]};
                    3'b010: data_out_buffer <= {1'b1, data_in_buffer[8], 1'b1, data_in_buffer[9], 1'b1, data_in_buffer[10], 1'b1, data_in_buffer[11]};
                    3'b011: data_out_buffer <= {1'b1, data_in_buffer[12], 1'b1, data_in_buffer[13], 1'b1, data_in_buffer[14], 1'b1, data_in_buffer[15]};
                    3'b100: data_out_buffer <= {1'b1, data_in_buffer[16], 1'b1, data_in_buffer[17], 1'b1, data_in_buffer[18], 1'b1, data_in_buffer[19]};
                    3'b101: data_out_buffer <= {1'b1, data_in_buffer[20], 1'b1, data_in_buffer[21], 1'b1, data_in_buffer[22], 1'b1, data_in_buffer[23]};
                    3'b110: data_out_buffer <= {5'b10101, channel_status_shift[23], 1'b1, parity};
                    default: data_out_buffer <= 8'b0;
                endcase
            end else begin
                data_out_buffer <= {data_out_buffer[6:0], 1'b0};
            end
        end
    end

    // Biphase mark encoding
    always @(posedge clk) begin
        if (rst)
            data_biphase <= 0;
        else if (data_out_buffer[7])
            data_biphase <= ~data_biphase;
    end

    always @(posedge clk)
        spdif_out <= data_biphase;

endmodule

verilog/spdif_transmit2/spdif_transmit2_tb.v
`timescale 1ns / 1ps

module spdif_transmit2_tb;

    // Parameters
    localparam real CLK_FREQ     = 24_576_000;     // 24.576 MHz clock
    localparam real SPDIF_BAUD   = 12_288_000;     // 12.288 Mbps SPDIF rate for 192kHz
    localparam real CLK_PERIOD   = 1_000_000_000.0 / CLK_FREQ; // ~40.69 ns

    // DUT inputs
    reg         rst;
    reg         clk;
    reg  [31:0] data_left;
    reg  [31:0] data_right;
    reg         validity;
    reg  [3:0]  sample_rate_code;

    // DUT output
    wire        spdif_out;

    // Instantiate DUT
    spdif_transmit2 dut (
        .rst(rst),
        .clk(clk),
        .data_left(data_left),
        .data_right(data_right),
        .validity(validity),
        .sample_rate_code(sample_rate_code),
        .spdif_out(spdif_out)
    );

    // Clock generation (~40.69ns period)
    initial clk = 0;
    always #(CLK_PERIOD / 2) clk = ~clk;

    // Stimulus
    initial begin
        $display("Starting SPDIF transmitter test...");
        $dumpfile("spdif_transmit2_tb.vcd");
        $dumpvars(0, spdif_transmit2_tb);

        // Initial values
        rst = 1;
        data_left = 0;
        data_right = 0;
        validity = 1;
        sample_rate_code = 4'b1100; // 192kHz

        # (10 * CLK_PERIOD);
        rst = 0;

        // Stimulus: send several sample pairs
        repeat (3) begin
            data_left  = $random & 32'h00FFFFFF;
            data_right = $random & 32'h00FFFFFF;
            validity   = 0;
            #(256 * CLK_PERIOD); // Wait ~1 audio frame (2 subframes × 64 bits = 128 SPDIF bits)
        end

        $display("Simulation complete.");
        $finish;
    end

endmodule

verilog/spdif_transmit2/spdif_transmit2_tb.vcd
$date
	Sat Sep 13 15:40:41 2025
$end
$version
	Icarus Verilog
$end
$timescale
	1ps
$end
$scope module spdif_transmit2_tb $end
$var wire 1 ! spdif_out $end
$var real 1 " CLK_FREQ $end
$var real 1 # CLK_PERIOD $end
$var real 1 $ SPDIF_BAUD $end
$var reg 1 % clk $end
$var reg 32 & data_left [31:0] $end
$var reg 32 ' data_right [31:0] $end
$var reg 1 ( rst $end
$var reg 4 ) sample_rate_code [3:0] $end
$var reg 1 * validity $end
$scope module dut $end
$var wire 1 % clk $end
$var wire 32 + data_left [31:0] $end
$var wire 32 , data_right [31:0] $end
$var wire 1 ( rst $end
$var wire 4 - sample_rate_code [3:0] $end
$var wire 1 * validity $end
$var reg 6 . bit_counter [5:0] $end
$var reg 24 / channel_status [23:0] $end
$var reg 24 0 channel_status_shift [23:0] $end
$var reg 1 1 data_biphase $end
$var reg 24 2 data_in_buffer [23:0] $end
$var reg 8 3 data_out_buffer [7:0] $end
$var reg 9 4 frame_counter [8:0] $end
$var reg 1 5 parity $end
$var reg 1 ! spdif_out $end
$upscope $end
$upscope $end
$enddefinitions $end
$comment Show the parameter values. $end
$dumpall
r12288000 $
r40.69010416666666 #
r24576000 "
$end
#0
$dumpvars
05
b0 4
b0 3
b0 2
01
b1000000000000001000000 0
b110000000000000001000000 /
b0 .
b1100 -
b0 ,
b0 +
1*
b1100 )
1(
b0 '
b0 &
0%
x!
$end
#20345
0!
b110000000000000001000000 0
1%
#40690
0%
#61035
1%
#81380
0%
#101725
1%
#122070
0%
#142415
1%
#162760
0%
#183105
1%
#203450
0%
#223795
1%
#244140
0%
#264485
1%
#284830
0%
#305175
1%
#325520
0%
#345865
1%
#366210
0%
#386555
1%
#406900
0%
#406901
0*
b100010010101111010000001 '
b100010010101111010000001 ,
b101010011010100100100 &
b101010011010100100100 +
0(
#427245
15
b1 .
1%
#447590
0%
#467935
b10 .
1%
#488280
0%
#508625
b11 .
1%
#528970
0%
#549315
b100 .
b1010100110101 2
1%
#569660
0%
#590005
05
b101 .
1%
#610350
0%
#630695
b110 .
1%
#651040
0%
#671385
b111 .
1%
#691730
0%
#712075
b1000 .
b11101110 3
1%
#732420
0%
#752765
11
b11011100 3
b1001 .
1%
#773110
0%
#793455
1!
b1010 .
b10111000 3
01
1%
#813800
0%
#834145
0!
11
b1110000 3
b1011 .
1%
#854490
0%
#874835
1!
b1100 .
b11100000 3
1%
#895180
0%
#915525
01
b11000000 3
b1101 .
1%
#935870
0%
#956215
0!
b1110 .
b10000000 3
11
1%
#976560
0%
#996905
1!
01
b0 3
b1111 .
1%
#1017250
0%
#1037595
0!
b10000 .
b11111010 3
1%
#1057940
0%
#1078285
11
b11110100 3
b10001 .
1%
#1098630
0%
#1118975
1!
b10010 .
b11101000 3
01
1%
#1139320
0%
#1159665
0!
11
b11010000 3
b10011 .
1%
#1180010
0%
#1200355
1!
b10100 .
b10100000 3
01
1%
#1220700
0%
#1241045
0!
11
b1000000 3
b10101 .
1%
#1261390
0%
#1281735
1!
b10110 .
b10000000 3
1%
#1302080
0%
#1322425
01
b0 3
b10111 .
1%
#1342770
0%
#1363115
0!
b11000 .
b11101110 3
1%
#1383460
0%
#1403805
11
b11011100 3
b11001 .
1%
#1424150
0%
#1444495
1!
b11010 .
b10111000 3
01
1%
#1464840
0%
#1485185
0!
11
b1110000 3
b11011 .
1%
#1505530
0%
#1525875
1!
b11100 .
b11100000 3
1%
#1546220
0%
#1566565
01
b11000000 3
b11101 .
1%
#1586910
0%
#1607255
0!
b11110 .
b10000000 3
11
1%
#1627600
0%
#1647945
1!
01
b0 3
b11111 .
1%
#1668290
0%
#1688635
0!
b100000 .
b11101010 3
1%
#1708980
0%
#1729325
11
b11010100 3
b100001 .
1%
#1749670
0%
#1770015
1!
b100010 .
b10101000 3
01
1%
#1790360
0%
#1810705
0!
11
b1010000 3
b100011 .
1%
#1831050
0%
#1851395
1!
b100100 .
b10100000 3
1%
#1871740
0%
#1892085
01
b1000000 3
b100101 .
1%
#1912430
0%
#1932775
0!
b100110 .
b10000000 3
1%
#1953120
0%
#1973465
11
b0 3
b100111 .
1%
#1993810
0%
#2014155
1!
b101000 .
b10101010 3
1%
#2034500
0%
#2054845
01
b1010100 3
b101001 .
1%
#2075190
0%
#2095535
0!
b101010 .
b10101000 3
1%
#2115880
0%
#2136225
11
b1010000 3
b101011 .
1%
#2156570
0%
#2176915
1!
b101100 .
b10100000 3
1%
#2197260
0%
#2217605
01
b1000000 3
b101101 .
1%
#2237950
0%
#2258295
0!
b101110 .
b10000000 3
1%
#2278640
0%
#2298985
11
b0 3
b101111 .
1%
#2319330
0%
#2339675
1!
b110000 .
b10101010 3
1%
#2360020
0%
#2380365
01
b1010100 3
b110001 .
1%
#2400710
0%
#2421055
0!
b110010 .
b10101000 3
1%
#2441400
0%
#2461745
11
b1010000 3
b110011 .
1%
#2482090
0%
#2502435
1!
b110100 .
b10100000 3
1%
#2522780
0%
#2543125
01
b1000000 3
b110101 .
1%
#2563470
0%
#2583815
0!
b110110 .
b10000000 3
1%
#2604160
0%
#2624505
11
b0 3
b110111 .
1%
#2644850
0%
#2665195
1!
b111000 .
b10101110 3
1%
#2685540
0%
#2705885
01
b1011100 3
b111001 .
1%
#2726230
0%
#2746575
0!
b111010 .
b10111000 3
1%
#2766920
0%
#2787265
11
b1110000 3
b111011 .
1%
#2807610
0%
#2827955
1!
b111100 .
b11100000 3
1%
#2848300
0%
#2868645
01
b11000000 3
b111101 .
1%
#2888990
0%
#2909335
0!
b111110 .
b10000000 3
11
1%
#2929680
0%
#2950025
1!
01
b0 3
b111111 .
1%
#2970370
0%
#2990715
0!
b0 .
b1 4
b10010110 3
1%
#3011060
0%
#3031405
11
b101100 3
b1 .
1%
#3051750
0%
#3072095
1!
b10 .
b1011000 3
1%
#3092440
0%
#3112785
b10110000 3
b11 .
1%
#3133130
0%
#3153475
b100 .
b1100000 3
01
1%
#3173820
0%
#3194165
0!
b11000000 3
b101 .
1%
#3214510
0%
#3234855
b110 .
b10000000 3
11
1%
#3255200
0%
#3275545
1!
01
b0 3
b111 .
1%
#3295890
0%
#3316235
0!
b1000 .
b11101110 3
1%
#3336580
0%
#3356925
11
b11011100 3
b1001 .
1%
#3377270
0%
#3397615
1!
b1010 .
b10111000 3
01
1%
#3417960
0%
#3438305
0!
11
b1110000 3
b1011 .
1%
#3458650
0%
#3478995
1!
b1100 .
b11100000 3
1%
#3499340
0%
#3519685
01
b11000000 3
b1101 .
1%
#3540030
0%
#3560375
0!
b1110 .
b10000000 3
11
1%
#3580720
0%
#3601065
1!
01
b0 3
b1111 .
1%
#3621410
0%
#3641755
0!
b10000 .
b11111010 3
1%
#3662100
0%
#3682445
11
b11110100 3
b10001 .
1%
#3702790
0%
#3723135
1!
b10010 .
b11101000 3
01
1%
#3743480
0%
#3763825
0!
11
b11010000 3
b10011 .
1%
#3784170
0%
#3804515
1!
b10100 .
b10100000 3
01
1%
#3824860
0%
#3845205
0!
11
b1000000 3
b10101 .
1%
#3865550
0%
#3885895
1!
b10110 .
b10000000 3
1%
#3906240
0%
#3926585
01
b0 3
b10111 .
1%
#3946930
0%
#3967275
0!
b11000 .
b11101110 3
1%
#3987620
0%
#4007965
11
b11011100 3
b11001 .
1%
#4028310
0%
#4048655
1!
b11010 .
b10111000 3
01
1%
#4069000
0%
#4089345
0!
11
b1110000 3
b11011 .
1%
#4109690
0%
#4130035
1!
b11100 .
b11100000 3
1%
#4150380
0%
#4170725
01
b11000000 3
b11101 .
1%
#4191070
0%
#4211415
0!
b11110 .
b10000000 3
11
1%
#4231760
0%
#4252105
1!
01
b0 3
b11111 .
1%
#4272450
0%
#4292795
0!
b100000 .
b11101010 3
1%
#4313140
0%
#4333485
11
b11010100 3
b100001 .
1%
#4353830
0%
#4374175
1!
b100010 .
b10101000 3
01
1%
#4394520
0%
#4414865
0!
11
b1010000 3
b100011 .
1%
#4435210
0%
#4455555
1!
b100100 .
b10100000 3
1%
#4475900
0%
#4496245
01
b1000000 3
b100101 .
1%
#4516590
0%
#4536935
0!
b100110 .
b10000000 3
1%
#4557280
0%
#4577625
11
b0 3
b100111 .
1%
#4597970
0%
#4618315
1!
b101000 .
b10101010 3
1%
#4638660
0%
#4659005
01
b1010100 3
b101001 .
1%
#4679350
0%
#4699695
0!
b101010 .
b10101000 3
1%
#4720040
0%
#4740385
11
b1010000 3
b101011 .
1%
#4760730
0%
#4781075
1!
b101100 .
b10100000 3
1%
#4801420
0%
#4821765
01
b1000000 3
b101101 .
1%
#4842110
0%
#4862455
0!
b101110 .
b10000000 3
1%
#4882800
0%
#4903145
11
b0 3
b101111 .
1%
#4923490
0%
#4943835
1!
b110000 .
b10101010 3
1%
#4964180
0%
#4984525
01
b1010100 3
b110001 .
1%
#5004870
0%
#5025215
0!
b110010 .
b10101000 3
1%
#5045560
0%
#5065905
11
b1010000 3
b110011 .
1%
#5086250
0%
#5106595
1!
b110100 .
b10100000 3
1%
#5126940
0%
#5147285
01
b1000000 3
b110101 .
1%
#5167630
0%
#5187975
0!
b110110 .
b10000000 3
1%
#5208320
0%
#5228665
11
b0 3
b110111 .
1%
#5249010
0%
#5269355
1!
b111000 .
b10101110 3
1%
#5289700
0%
#5310045
01
b1011100 3
b111001 .
1%
#5330390
0%
#5350735
0!
b111010 .
b10111000 3
1%
#5371080
0%
#5391425
11
b1110000 3
b111011 .
1%
#5411770
0%
#5432115
1!
b111100 .
b11100000 3
1%
#5452460
0%
#5472805
01
b11000000 3
b111101 .
1%
#5493150
0%
#5513495
0!
b111110 .
b10000000 3
11
1%
#5533840
0%
#5554185
1!
01
b0 3
b111111 .
1%
#5574530
0%
#5594875
0!
b0 .
b10 4
b100000000000000010000000 0
b10010011 3
1%
#5615220
0%
#5635565
11
b100110 3
b1 .
1%
#5655910
0%
#5676255
1!
b10 .
b1001100 3
1%
#5696600
0%
#5716945
b10011000 3
b11 .
1%
#5737290
0%
#5757635
b100 .
b110000 3
01
1%
#5777980
0%
#5798325
0!
b1100000 3
b101 .
1%
#5818670
0%
#5839015
b110 .
b11000000 3
1%
#5859360
0%
#5879705
11
b10000000 3
b111 .
1%
#5900050
0%
#5920395
1!
b1000 .
b11101110 3
01
1%
#5940740
0%
#5961085
0!
11
b11011100 3
b1001 .
1%
#5981430
0%
#6001775
1!
b1010 .
b10111000 3
01
1%
#6022120
0%
#6042465
0!
11
b1110000 3
b1011 .
1%
#6062810
0%
#6083155
1!
b1100 .
b11100000 3
1%
#6103500
0%
#6123845
01
b11000000 3
b1101 .
1%
#6144190
0%
#6164535
0!
b1110 .
b10000000 3
11
1%
#6184880
0%
#6205225
1!
01
b0 3
b1111 .
1%
#6225570
0%
#6245915
0!
b10000 .
b11111010 3
1%
#6266260
0%
#6286605
11
b11110100 3
b10001 .
1%
#6306950
0%
#6327295
1!
b10010 .
b11101000 3
01
1%
#6347640
0%
#6367985
0!
11
b11010000 3
b10011 .
1%
#6388330
0%
#6408675
1!
b10100 .
b10100000 3
01
1%
#6429020
0%
#6449365
0!
11
b1000000 3
b10101 .
1%
#6469710
0%
#6490055
1!
b10110 .
b10000000 3
1%
#6510400
0%
#6530745
01
b0 3
b10111 .
1%
#6551090
0%
#6571435
0!
b11000 .
b11101110 3
1%
#6591780
0%
#6612125
11
b11011100 3
b11001 .
1%
#6632470
0%
#6652815
1!
b11010 .
b10111000 3
01
1%
#6673160
0%
#6693505
0!
11
b1110000 3
b11011 .
1%
#6713850
0%
#6734195
1!
b11100 .
b11100000 3
1%
#6754540
0%
#6774885
01
b11000000 3
b11101 .
1%
#6795230
0%
#6815575
0!
b11110 .
b10000000 3
11
1%
#6835920
0%
#6856265
1!
01
b0 3
b11111 .
1%
#6876610
0%
#6896955
0!
b100000 .
b11101010 3
1%
#6917300
0%
#6937645
11
b11010100 3
b100001 .
1%
#6957990
0%
#6978335
1!
b100010 .
b10101000 3
01
1%
#6998680
0%
#7019025
0!
11
b1010000 3
b100011 .
1%
#7039370
0%
#7059715
1!
b100100 .
b10100000 3
1%
#7080060
0%
#7100405
01
b1000000 3
b100101 .
1%
#7120750
0%
#7141095
0!
b100110 .
b10000000 3
1%
#7161440
0%
#7181785
11
b0 3
b100111 .
1%
#7202130
0%
#7222475
1!
b101000 .
b10101010 3
1%
#7242820
0%
#7263165
01
b1010100 3
b101001 .
1%
#7283510
0%
#7303855
0!
b101010 .
b10101000 3
1%
#7324200
0%
#7344545
11
b1010000 3
b101011 .
1%
#7364890
0%
#7385235
1!
b101100 .
b10100000 3
1%
#7405580
0%
#7425925
01
b1000000 3
b101101 .
1%
#7446270
0%
#7466615
0!
b101110 .
b10000000 3
1%
#7486960
0%
#7507305
11
b0 3
b101111 .
1%
#7527650
0%
#7547995
1!
b110000 .
b10101010 3
1%
#7568340
0%
#7588685
01
b1010100 3
b110001 .
1%
#7609030
0%
#7629375
0!
b110010 .
b10101000 3
1%
#7649720
0%
#7670065
11
b1010000 3
b110011 .
1%
#7690410
0%
#7710755
1!
b110100 .
b10100000 3
1%
#7731100
0%
#7751445
01
b1000000 3
b110101 .
1%
#7771790
0%
#7792135
0!
b110110 .
b10000000 3
1%
#7812480
0%
#7832825
11
b0 3
b110111 .
1%
#7853170
0%
#7873515
1!
b111000 .
b10101110 3
1%
#7893860
0%
#7914205
01
b1011100 3
b111001 .
1%
#7934550
0%
#7954895
0!
b111010 .
b10111000 3
1%
#7975240
0%
#7995585
11
b1110000 3
b111011 .
1%
#8015930
0%
#8036275
1!
b111100 .
b11100000 3
1%
#8056620
0%
#8076965
01
b11000000 3
b111101 .
1%
#8097310
0%
#8117655
0!
b111110 .
b10000000 3
11
1%
#8138000
0%
#8158345
1!
01
b0 3
b111111 .
1%
#8178690
0%
#8199035
0!
b0 .
b11 4
b10010110 3
1%
#8219380
0%
#8239725
11
b101100 3
b1 .
1%
#8260070
0%
#8280415
1!
b10 .
b1011000 3
1%
#8300760
0%
#8321105
b10110000 3
b11 .
1%
#8341450
0%
#8361795
b100 .
b1100000 3
01
1%
#8382140
0%
#8402485
0!
b11000000 3
b101 .
1%
#8422830
0%
#8443175
b110 .
b10000000 3
11
1%
#8463520
0%
#8483865
1!
01
b0 3
b111 .
1%
#8504210
0%
#8524555
0!
b1000 .
b11101110 3
1%
#8544900
0%
#8565245
11
b11011100 3
b1001 .
1%
#8585590
0%
#8605935
1!
b1010 .
b10111000 3
01
1%
#8626280
0%
#8646625
0!
11
b1110000 3
b1011 .
1%
#8666970
0%
#8687315
1!
b1100 .
b11100000 3
1%
#8707660
0%
#8728005
01
b11000000 3
b1101 .
1%
#8748350
0%
#8768695
0!
b1110 .
b10000000 3
11
1%
#8789040
0%
#8809385
1!
01
b0 3
b1111 .
1%
#8829730
0%
#8850075
0!
b10000 .
b11111010 3
1%
#8870420
0%
#8890765
11
b11110100 3
b10001 .
1%
#8911110
0%
#8931455
1!
b10010 .
b11101000 3
01
1%
#8951800
0%
#8972145
0!
11
b11010000 3
b10011 .
1%
#8992490
0%
#9012835
1!
b10100 .
b10100000 3
01
1%
#9033180
0%
#9053525
0!
11
b1000000 3
b10101 .
1%
#9073870
0%
#9094215
1!
b10110 .
b10000000 3
1%
#9114560
0%
#9134905
01
b0 3
b10111 .
1%
#9155250
0%
#9175595
0!
b11000 .
b11101110 3
1%
#9195940
0%
#9216285
11
b11011100 3
b11001 .
1%
#9236630
0%
#9256975
1!
b11010 .
b10111000 3
01
1%
#9277320
0%
#9297665
0!
11
b1110000 3
b11011 .
1%
#9318010
0%
#9338355
1!
b11100 .
b11100000 3
1%
#9358700
0%
#9379045
01
b11000000 3
b11101 .
1%
#9399390
0%
#9419735
0!
b11110 .
b10000000 3
11
1%
#9440080
0%
#9460425
1!
01
b0 3
b11111 .
1%
#9480770
0%
#9501115
0!
b100000 .
b11101010 3
1%
#9521460
0%
#9541805
11
b11010100 3
b100001 .
1%
#9562150
0%
#9582495
1!
b100010 .
b10101000 3
01
1%
#9602840
0%
#9623185
0!
11
b1010000 3
b100011 .
1%
#9643530
0%
#9663875
1!
b100100 .
b10100000 3
1%
#9684220
0%
#9704565
01
b1000000 3
b100101 .
1%
#9724910
0%
#9745255
0!
b100110 .
b10000000 3
1%
#9765600
0%
#9785945
11
b0 3
b100111 .
1%
#9806290
0%
#9826635
1!
b101000 .
b10101010 3
1%
#9846980
0%
#9867325
01
b1010100 3
b101001 .
1%
#9887670
0%
#9908015
0!
b101010 .
b10101000 3
1%
#9928360
0%
#9948705
11
b1010000 3
b101011 .
1%
#9969050
0%
#9989395
1!
b101100 .
b10100000 3
1%
#10009740
0%
#10030085
01
b1000000 3
b101101 .
1%
#10050430
0%
#10070775
0!
b101110 .
b10000000 3
1%
#10091120
0%
#10111465
11
b0 3
b101111 .
1%
#10131810
0%
#10152155
1!
b110000 .
b10101010 3
1%
#10172500
0%
#10192845
01
b1010100 3
b110001 .
1%
#10213190
0%
#10233535
0!
b110010 .
b10101000 3
1%
#10253880
0%
#10274225
11
b1010000 3
b110011 .
1%
#10294570
0%
#10314915
1!
b110100 .
b10100000 3
1%
#10335260
0%
#10355605
01
b1000000 3
b110101 .
1%
#10375950
0%
#10396295
0!
b110110 .
b10000000 3
1%
#10416640
0%
#10436985
11
b0 3
b110111 .
1%
#10457330
0%
#10477675
1!
b111000 .
b10101110 3
1%
#10498020
0%
#10518365
01
b1011100 3
b111001 .
1%
#10538710
0%
#10559055
0!
b111010 .
b10111000 3
1%
#10579400
0%
#10599745
11
b1110000 3
b111011 .
1%
#10620090
0%
#10640435
1!
b111100 .
b11100000 3
1%
#10660780
0%
#10681125
01
b11000000 3
b111101 .
1%
#10701470
0%
#10721815
0!
b111110 .
b10000000 3
11
1%
#10742160
0%
#10762505
1!
01
b0 3
b111111 .
1%
#10782850
0%
#10803195
0!
b0 .
b100 4
b100000000 0
b10010011 3
1%
#10823540
0%
#10823568
b111100000101011001100011 '
b111100000101011001100011 ,
b100001001101011000001001 &
b100001001101011000001001 +
#10843885
11
b100110 3
15
b1 .
1%
#10864230
0%
#10884575
1!
b10 .
b1001100 3
1%
#10904920
0%
#10925265
b10011000 3
b11 .
1%
#10945610
0%
#10965955
b100 .
b1000010011010110 2
b110000 3
01
1%
#10986300
0%
#11006645
0!
b1100000 3
b101 .
1%
#11026990
0%
#11047335
b110 .
b11000000 3
1%
#11067680
0%
#11088025
11
b10000000 3
b111 .
1%
#11108370
0%
#11128715
1!
b1000 .
b10111110 3
01
1%
#11149060
0%
#11169405
0!
11
b1111100 3
b1001 .
1%
#11189750
0%
#11210095
1!
b1010 .
b11111000 3
1%
#11230440
0%
#11250785
01
b11110000 3
b1011 .
1%
#11271130
0%
#11291475
0!
b1100 .
b11100000 3
11
1%
#11311820
0%
#11332165
1!
01
b11000000 3
b1101 .
1%
#11352510
0%
#11372855
0!
b1110 .
b10000000 3
11
1%
#11393200
0%
#11413545
1!
01
b0 3
b1111 .
1%
#11433890
0%
#11454235
0!
b10000 .
b11101111 3
1%
#11474580
0%
#11494925
11
b11011110 3
b10001 .
1%
#11515270
0%
#11535615
1!
b10010 .
b10111100 3
01
1%
#11555960
0%
#11576305
0!
11
b1111000 3
b10011 .
1%
#11596650
0%
#11616995
1!
b10100 .
b11110000 3
1%
#11637340
0%
#11657685
01
b11100000 3
b10101 .
1%
#11678030
0%
#11698375
0!
b10110 .
b11000000 3
11
1%
#11718720
0%
#11739065
1!
01
b10000000 3
b10111 .
1%
#11759410
0%
#11779755
0!
b11000 .
b10101110 3
11
1%
#11800100
0%
#11820445
1!
01
b1011100 3
b11001 .
1%
#11840790
0%
#11861135
0!
b11010 .
b10111000 3
1%
#11881480
0%
#11901825
11
b1110000 3
b11011 .
1%
#11922170
0%
#11942515
1!
b11100 .
b11100000 3
1%
#11962860
0%
#11983205
01
b11000000 3
b11101 .
1%
#12003550
0%
#12023895
0!
b11110 .
b10000000 3
11
1%
#12044240
0%
#12064585
1!
01
b0 3
b11111 .
1%
#12084930
0%
#12105275
0!
b100000 .
b10101011 3
1%
#12125620
0%
#12145965
11
b1010110 3
b100001 .
1%
#12166310
0%
#12186655
1!
b100010 .
b10101100 3
1%
#12207000
0%
#12227345
01
b1011000 3
b100011 .
1%
#12247690
0%
#12268035
0!
b100100 .
b10110000 3
1%
#12288380
0%
#12308725
11
b1100000 3
b100101 .
1%
#12329070
0%
#12349415
1!
b100110 .
b11000000 3
1%
#12369760
0%
#12390105
01
b10000000 3
b100111 .
1%
#12410450
0%
#12430795
0!
b101000 .
b10101010 3
11
1%
#12451140
0%
#12471485
1!
01
b1010100 3
b101001 .
1%
#12491830
0%
#12512175
0!
b101010 .
b10101000 3
1%
#12532520
0%
#12552865
11
b1010000 3
b101011 .
1%
#12573210
0%
#12593555
1!
b101100 .
b10100000 3
1%
#12613900
0%
#12634245
01
b1000000 3
b101101 .
1%
#12654590
0%
#12674935
0!
b101110 .
b10000000 3
1%
#12695280
0%
#12715625
11
b0 3
b101111 .
1%
#12735970
0%
#12756315
1!
b110000 .
b10101010 3
1%
#12776660
0%
#12797005
01
b1010100 3
b110001 .
1%
#12817350
0%
#12837695
0!
b110010 .
b10101000 3
1%
#12858040
0%
#12878385
11
b1010000 3
b110011 .
1%
#12898730
0%
#12919075
1!
b110100 .
b10100000 3
1%
#12939420
0%
#12959765
01
b1000000 3
b110101 .
1%
#12980110
0%
#13000455
0!
b110110 .
b10000000 3
1%
#13020800
0%
#13041145
11
b0 3
b110111 .
1%
#13061490
0%
#13081835
1!
b111000 .
b10101011 3
1%
#13102180
0%
#13122525
01
b1010110 3
b111001 .
1%
#13142870
0%
#13163215
0!
b111010 .
b10101100 3
1%
#13183560
0%
#13203905
11
b1011000 3
b111011 .
1%
#13224250
0%
#13244595
1!
b111100 .
b10110000 3
1%
#13264940
0%
#13285285
01
b1100000 3
b111101 .
1%
#13305630
0%
#13325975
0!
b111110 .
b11000000 3
1%
#13346320
0%
#13366665
11
b10000000 3
b111111 .
1%
#13387010
0%
#13407355
1!
b0 .
b101 4
b10010110 3
01
1%
#13427700
0%
#13448045
0!
11
b101100 3
b1 .
1%
#13468390
0%
#13488735
1!
b10 .
b1011000 3
1%
#13509080
0%
#13529425
b10110000 3
b11 .
1%
#13549770
0%
#13570115
b100 .
b1100000 3
01
1%
#13590460
0%
#13610805
0!
b11000000 3
b101 .
1%
#13631150
0%
#13651495
b110 .
b10000000 3
11
1%
#13671840
0%
#13692185
1!
01
b0 3
b111 .
1%
#13712530
0%
#13732875
0!
b1000 .
b10111110 3
1%
#13753220
0%
#13773565
11
b1111100 3
b1001 .
1%
#13793910
0%
#13814255
1!
b1010 .
b11111000 3
1%
#13834600
0%
#13854945
01
b11110000 3
b1011 .
1%
#13875290
0%
#13895635
0!
b1100 .
b11100000 3
11
1%
#13915980
0%
#13936325
1!
01
b11000000 3
b1101 .
1%
#13956670
0%
#13977015
0!
b1110 .
b10000000 3
11
1%
#13997360
0%
#14017705
1!
01
b0 3
b1111 .
1%
#14038050
0%
#14058395
0!
b10000 .
b11101111 3
1%
#14078740
0%
#14099085
11
b11011110 3
b10001 .
1%
#14119430
0%
#14139775
1!
b10010 .
b10111100 3
01
1%
#14160120
0%
#14180465
0!
11
b1111000 3
b10011 .
1%
#14200810
0%
#14221155
1!
b10100 .
b11110000 3
1%
#14241500
0%
#14261845
01
b11100000 3
b10101 .
1%
#14282190
0%
#14302535
0!
b10110 .
b11000000 3
11
1%
#14322880
0%
#14343225
1!
01
b10000000 3
b10111 .
1%
#14363570
0%
#14383915
0!
b11000 .
b10101110 3
11
1%
#14404260
0%
#14424605
1!
01
b1011100 3
b11001 .
1%
#14444950
0%
#14465295
0!
b11010 .
b10111000 3
1%
#14485640
0%
#14505985
11
b1110000 3
b11011 .
1%
#14526330
0%
#14546675
1!
b11100 .
b11100000 3
1%
#14567020
0%
#14587365
01
b11000000 3
b11101 .
1%
#14607710
0%
#14628055
0!
b11110 .
b10000000 3
11
1%
#14648400
0%
#14668745
1!
01
b0 3
b11111 .
1%
#14689090
0%
#14709435
0!
b100000 .
b10101011 3
1%
#14729780
0%
#14750125
11
b1010110 3
b100001 .
1%
#14770470
0%
#14790815
1!
b100010 .
b10101100 3
1%
#14811160
0%
#14831505
01
b1011000 3
b100011 .
1%
#14851850
0%
#14872195
0!
b100100 .
b10110000 3
1%
#14892540
0%
#14912885
11
b1100000 3
b100101 .
1%
#14933230
0%
#14953575
1!
b100110 .
b11000000 3
1%
