verilog/spdif_transmit/spdif_transmit.v
module spdif_transmit (
    input  wire        rst,         // Active high reset
    input  wire        clk,         // System clock (must be much faster than SPDIF bit rate)
    input  wire [31:0] data_left,   // Left channel data
    input  wire [31:0] data_right,  // Right channel data
    output reg         spdif_out    // SPDIF output signal
);

    // Parameters for SPDIF bit rate and system clock
    parameter SPDIF_BAUD = 3072000; // 3.072 Mbps for 48kHz audio
    parameter CLK_FREQ   = 12288000; // Example: 12.288 MHz system clock
    localparam CLK_DIV = CLK_FREQ / SPDIF_BAUD;

    reg [15:0] clk_cnt = 0;
    reg        spdif_clk = 0;

    // Generate SPDIF bit clock
    always @(posedge clk or posedge rst) begin
        if (rst) begin
            clk_cnt <= 0;
            spdif_clk <= 0;
        end else begin
            if (clk_cnt == CLK_DIV - 1) begin
                clk_cnt <= 0;
                spdif_clk <= ~spdif_clk; // Toggle SPDIF clock
            end else begin
                clk_cnt <= clk_cnt + 1;
            end 
        end
    end

    // Example: output a simple toggling pattern (replace with real BMC encoding)
    reg [7:0] frame = 8'b10110010;
    reg [2:0] idx = 0;

    always @(negedge spdif_clk or posedge rst) begin
        if (rst) begin
            idx   <= 0;
        end else begin
            idx   <= (idx == 7) ? 0 : idx + 1;
        end
    end


    reg Q1 = 0, Q2 = 0; // BMC encoding states
    always @(*)
        spdif_out <= Q1 ^ Q2; // Biphase Mark Coding (BMC) signal

    wire Q1_pre = frame[idx] ^ Q1;
    wire Q2_pre = !Q2;

    always @(negedge spdif_clk) begin
        Q1 <= Q1_pre; 
    end

    always @(posedge spdif_clk) begin
        Q2 <= Q2_pre;
    end

endmodule

verilog/spdif_transmit/spdif_transmit_tb.v
`timescale 1ns/1ns

module spdif_transmit_tb;

  reg clk = 0;
  always #50 clk = ~clk; // 10 MHz clock

  reg rst = 1;
  initial begin
    repeat(10) @(posedge clk);
    rst = 0;
  end

  reg [31:0] data_left = 0;
  reg [31:0] data_right = 0;

  // Instantiate DUT
  spdif_transmit dut (
    .rst(rst),
    .clk(clk),
    .data_left(data_left),
    .data_right(data_right),
    .spdif_out(spdif_out)
  );

  initial begin
    $dumpfile("spdif_transmit_tb.vcd");
    $dumpvars(0, spdif_transmit_tb);
    @(negedge rst); // Wait for reset deassertion
    @(posedge clk);
    data_left  = $random;
    data_right = $random;
    repeat(200) @(posedge clk);    
    $finish;
  end

endmodule

verilog/spdif_transmit/spdif_transmit_tb.vcd
$date
	Sun Aug 03 18:14:41 2025
$end
$version
	Icarus Verilog
$end
$timescale
	1ps
$end
$scope module spdif_transmit_tb $end
$var wire 1 ! spdif_out $end
$var reg 1 " clk $end
$var reg 32 # data_left [31:0] $end
$var reg 32 $ data_right [31:0] $end
$var reg 1 % rst $end
$scope module dut $end
$var wire 1 & Q1_pre $end
$var wire 1 " clk $end
$var wire 32 ' data_left [31:0] $end
$var wire 32 ( data_right [31:0] $end
$var wire 1 % rst $end
$var wire 1 ) Q2_pre $end
$var reg 1 * Q1 $end
$var reg 1 + Q2 $end
$var reg 16 , clk_cnt [15:0] $end
$var reg 8 - frame [7:0] $end
$var reg 3 . idx [2:0] $end
$var reg 1 / spdif_clk $end
$var reg 1 ! spdif_out $end
$upscope $end
$upscope $end
$enddefinitions $end
#0
$dumpvars
0/
b0 .
b10110010 -
b0 ,
0+
0*
1)
b0 (
b0 '
0&
1%
b0 $
b0 #
0"
0!
$end
#50000
1"
#100000
0"
#150000
1"
#200000
0"
#250000
1"
#300000
0"
#350000
1"
#400000
0"
#450000
1"
#500000
0"
#550000
1"
#600000
0"
#650000
1"
#700000
0"
#750000
1"
#800000
0"
#850000
1"
#900000
0"
#950000
b1 ,
0%
1"
#1000000
0"
#1050000
b10 ,
b11000000100010010101111010000001 $
b11000000100010010101111010000001 (
b10010000101010011010100100100 #
b10010000101010011010100100100 '
1"
#1100000
0"
#1150000
b11 ,
1"
#1200000
0"
#1250000
1!
0)
1+
1/
b0 ,
1"
#1300000
0"
#1350000
b1 ,
1"
#1400000
0"
#1450000
b10 ,
1"
#1500000
0"
#1550000
b11 ,
1"
#1600000
0"
#1650000
1&
b1 .
0/
b0 ,
1"
#1700000
0"
#1750000
b1 ,
1"
#1800000
0"
#1850000
b10 ,
1"
#1900000
0"
#1950000
b11 ,
1"
#2000000
0"
#2050000
0!
1)
0+
1/
b0 ,
1"
#2100000
0"
#2150000
b1 ,
1"
#2200000
0"
#2250000
b10 ,
1"
#2300000
0"
#2350000
b11 ,
1"
#2400000
0"
#2450000
1!
1*
b10 .
0/
b0 ,
1"
#2500000
0"
#2550000
b1 ,
1"
#2600000
0"
#2650000
b10 ,
1"
#2700000
0"
#2750000
b11 ,
1"
#2800000
0"
#2850000
0!
0)
1+
1/
b0 ,
1"
#2900000
0"
#2950000
b1 ,
1"
#3000000
0"
#3050000
b10 ,
1"
#3100000
0"
#3150000
b11 ,
1"
#3200000
0"
#3250000
b11 .
0/
b0 ,
1"
#3300000
0"
#3350000
b1 ,
1"
#3400000
0"
#3450000
b10 ,
1"
#3500000
0"
#3550000
b11 ,
1"
#3600000
0"
#3650000
1!
1)
0+
1/
b0 ,
1"
#3700000
0"
#3750000
b1 ,
1"
#3800000
0"
#3850000
b10 ,
1"
#3900000
0"
#3950000
b11 ,
1"
#4000000
0"
#4050000
0&
b100 .
0/
b0 ,
1"
#4100000
0"
#4150000
b1 ,
1"
#4200000
0"
#4250000
b10 ,
1"
#4300000
0"
#4350000
b11 ,
1"
#4400000
0"
#4450000
0!
0)
1+
1/
b0 ,
1"
#4500000
0"
#4550000
b1 ,
1"
#4600000
0"
#4650000
b10 ,
1"
#4700000
0"
#4750000
b11 ,
1"
#4800000
0"
#4850000
1!
1&
0*
b101 .
0/
b0 ,
1"
#4900000
0"
#4950000
b1 ,
1"
#5000000
0"
#5050000
b10 ,
1"
#5100000
0"
#5150000
b11 ,
1"
#5200000
0"
#5250000
0!
1)
0+
1/
b0 ,
1"
#5300000
0"
#5350000
b1 ,
1"
#5400000
0"
#5450000
b10 ,
1"
#5500000
0"
#5550000
b11 ,
1"
#5600000
0"
#5650000
1!
1*
b110 .
0/
b0 ,
1"
#5700000
0"
#5750000
b1 ,
1"
#5800000
0"
#5850000
b10 ,
1"
#5900000
0"
#5950000
b11 ,
1"
#6000000
0"
#6050000
0!
0)
1+
1/
b0 ,
1"
#6100000
0"
#6150000
b1 ,
1"
#6200000
0"
#6250000
b10 ,
1"
#6300000
0"
#6350000
b11 ,
1"
#6400000
0"
#6450000
0&
b111 .
0/
b0 ,
1"
#6500000
0"
#6550000
b1 ,
1"
#6600000
0"
#6650000
b10 ,
1"
#6700000
0"
#6750000
b11 ,
1"
#6800000
0"
#6850000
1!
1)
0+
1/
b0 ,
1"
#6900000
0"
#6950000
b1 ,
1"
#7000000
0"
#7050000
b10 ,
1"
#7100000
0"
#7150000
b11 ,
1"
#7200000
0"
#7250000
0!
0*
b0 .
0/
b0 ,
1"
#7300000
0"
#7350000
b1 ,
1"
#7400000
0"
#7450000
b10 ,
1"
#7500000
0"
#7550000
b11 ,
1"
#7600000
0"
#7650000
1!
0)
1+
1/
b0 ,
1"
#7700000
0"
#7750000
b1 ,
1"
#7800000
0"
#7850000
b10 ,
1"
#7900000
0"
#7950000
b11 ,
1"
#8000000
0"
#8050000
1&
b1 .
0/
b0 ,
1"
#8100000
0"
#8150000
b1 ,
1"
#8200000
0"
#8250000
b10 ,
1"
#8300000
0"
#8350000
b11 ,
1"
#8400000
0"
#8450000
0!
1)
0+
1/
b0 ,
1"
#8500000
0"
#8550000
b1 ,
1"
#8600000
0"
#8650000
b10 ,
1"
#8700000
0"
#8750000
b11 ,
1"
#8800000
0"
#8850000
1!
1*
b10 .
0/
b0 ,
1"
#8900000
0"
#8950000
b1 ,
1"
#9000000
0"
#9050000
b10 ,
1"
#9100000
0"
#9150000
b11 ,
1"
#9200000
0"
#9250000
0!
0)
1+
1/
b0 ,
1"
#9300000
0"
#9350000
b1 ,
1"
#9400000
0"
#9450000
b10 ,
1"
#9500000
0"
#9550000
b11 ,
1"
#9600000
0"
#9650000
b11 .
0/
b0 ,
1"
#9700000
0"
#9750000
b1 ,
1"
#9800000
0"
#9850000
b10 ,
1"
#9900000
0"
#9950000
b11 ,
1"
#10000000
0"
#10050000
1!
1)
0+
1/
b0 ,
1"
#10100000
0"
#10150000
b1 ,
1"
#10200000
0"
#10250000
b10 ,
1"
#10300000
0"
#10350000
b11 ,
1"
#10400000
0"
#10450000
0&
b100 .
0/
b0 ,
1"
#10500000
0"
#10550000
b1 ,
1"
#10600000
0"
#10650000
b10 ,
1"
#10700000
0"
#10750000
b11 ,
1"
#10800000
0"
#10850000
0!
0)
1+
1/
b0 ,
1"
#10900000
0"
#10950000
b1 ,
1"
#11000000
0"
#11050000
b10 ,
1"
#11100000
0"
#11150000
b11 ,
1"
#11200000
0"
#11250000
1!
1&
0*
b101 .
0/
b0 ,
1"
#11300000
0"
#11350000
b1 ,
1"
#11400000
0"
#11450000
b10 ,
1"
#11500000
0"
#11550000
b11 ,
1"
#11600000
0"
#11650000
0!
1)
0+
1/
b0 ,
1"
#11700000
0"
#11750000
b1 ,
1"
#11800000
0"
#11850000
b10 ,
1"
#11900000
0"
#11950000
b11 ,
1"
#12000000
0"
#12050000
1!
1*
b110 .
0/
b0 ,
1"
#12100000
0"
#12150000
b1 ,
1"
#12200000
0"
#12250000
b10 ,
1"
#12300000
0"
#12350000
b11 ,
1"
#12400000
0"
#12450000
0!
0)
1+
1/
b0 ,
1"
#12500000
0"
#12550000
b1 ,
1"
#12600000
0"
#12650000
b10 ,
1"
#12700000
0"
#12750000
b11 ,
1"
#12800000
0"
#12850000
0&
b111 .
0/
b0 ,
1"
#12900000
0"
#12950000
b1 ,
1"
#13000000
0"
#13050000
b10 ,
1"
#13100000
0"
#13150000
b11 ,
1"
#13200000
0"
#13250000
1!
1)
0+
1/
b0 ,
1"
#13300000
0"
#13350000
b1 ,
1"
#13400000
0"
#13450000
b10 ,
1"
#13500000
0"
#13550000
b11 ,
1"
#13600000
0"
#13650000
0!
0*
b0 .
0/
b0 ,
1"
#13700000
0"
#13750000
b1 ,
1"
#13800000
0"
#13850000
b10 ,
1"
#13900000
0"
#13950000
b11 ,
1"
#14000000
0"
#14050000
1!
0)
1+
1/
b0 ,
1"
#14100000
0"
#14150000
b1 ,
1"
#14200000
0"
#14250000
b10 ,
1"
#14300000
0"
#14350000
b11 ,
1"
#14400000
0"
#14450000
1&
b1 .
0/
b0 ,
1"
#14500000
0"
#14550000
b1 ,
1"
#14600000
0"
#14650000
b10 ,
1"
#14700000
0"
#14750000
b11 ,
1"
#14800000
0"
#14850000
0!
1)
0+
1/
b0 ,
1"
#14900000
0"
#14950000
b1 ,
1"
#15000000
0"
#15050000
b10 ,
1"
#15100000
0"
#15150000
b11 ,
1"
#15200000
0"
#15250000
1!
1*
b10 .
0/
b0 ,
1"
#15300000
0"
#15350000
b1 ,
1"
#15400000
0"
#15450000
b10 ,
1"
#15500000
0"
#15550000
b11 ,
1"
#15600000
0"
#15650000
0!
0)
1+
1/
b0 ,
1"
#15700000
0"
#15750000
b1 ,
1"
#15800000
0"
#15850000
b10 ,
1"
#15900000
0"
#15950000
b11 ,
1"
#16000000
0"
#16050000
b11 .
0/
b0 ,
1"
#16100000
0"
#16150000
b1 ,
1"
#16200000
0"
#16250000
b10 ,
1"
#16300000
0"
#16350000
b11 ,
1"
#16400000
0"
#16450000
1!
1)
0+
1/
b0 ,
1"
#16500000
0"
#16550000
b1 ,
1"
#16600000
0"
#16650000
b10 ,
1"
#16700000
0"
#16750000
b11 ,
1"
#16800000
0"
#16850000
0&
b100 .
0/
b0 ,
1"
#16900000
0"
#16950000
b1 ,
1"
#17000000
0"
#17050000
b10 ,
1"
#17100000
0"
#17150000
b11 ,
1"
#17200000
0"
#17250000
0!
0)
1+
1/
b0 ,
1"
#17300000
0"
#17350000
b1 ,
1"
#17400000
0"
#17450000
b10 ,
1"
#17500000
0"
#17550000
b11 ,
1"
#17600000
0"
#17650000
1!
1&
0*
b101 .
0/
b0 ,
1"
#17700000
0"
#17750000
b1 ,
1"
#17800000
0"
#17850000
b10 ,
1"
#17900000
0"
#17950000
b11 ,
1"
#18000000
0"
#18050000
0!
1)
0+
1/
b0 ,
1"
#18100000
0"
#18150000
b1 ,
1"
#18200000
0"
#18250000
b10 ,
1"
#18300000
0"
#18350000
b11 ,
1"
#18400000
0"
#18450000
1!
1*
b110 .
0/
b0 ,
1"
#18500000
0"
#18550000
b1 ,
1"
#18600000
0"
#18650000
b10 ,
1"
#18700000
0"
#18750000
b11 ,
1"
#18800000
0"
#18850000
0!
0)
1+
1/
b0 ,
1"
#18900000
0"
#18950000
b1 ,
1"
#19000000
0"
#19050000
b10 ,
1"
#19100000
0"
#19150000
b11 ,
1"
#19200000
0"
#19250000
0&
b111 .
0/
b0 ,
1"
#19300000
0"
#19350000
b1 ,
1"
#19400000
0"
#19450000
b10 ,
1"
#19500000
0"
#19550000
b11 ,
1"
#19600000
0"
#19650000
1!
1)
0+
1/
b0 ,
1"
#19700000
0"
#19750000
b1 ,
1"
#19800000
0"
#19850000
b10 ,
1"
#19900000
0"
#19950000
b11 ,
1"
#20000000
0"
#20050000
0!
0*
b0 .
0/
b0 ,
1"
#20100000
0"
#20150000
b1 ,
1"
#20200000
0"
#20250000
b10 ,
1"
#20300000
0"
#20350000
b11 ,
1"
#20400000
0"
#20450000
1!
0)
1+
1/
b0 ,
1"
#20500000
0"
#20550000
b1 ,
1"
#20600000
0"
#20650000
b10 ,
1"
#20700000
0"
#20750000
b11 ,
1"
#20800000
0"
#20850000
1&
b1 .
0/
b0 ,
1"
#20900000
0"
#20950000
b1 ,
1"
#21000000
0"
#21050000
b10 ,
1"
