verilog/spdif_transmit/spdif_transmit.v
module spdif_transmit (
    input  wire        rst,
    input  wire        clk,
    input  wire [31:0] data_left,
    input  wire [31:0] data_right,
    input  wire        validity,
    input  wire [3:0]  sample_rate_code,
    output reg         spdif_out
);

    // Parameters for 192kHz
    parameter SPDIF_BAUD = 12288000; // 12.288 Mbps
    parameter CLK_FREQ   = 24576000; // 24.576 MHz
    localparam CLK_DIV = 2;

    // channel status word
    reg [191:0] ch_status_left  = 192'b0;
    reg [191:0] ch_status_right = 192'b0;

    always @(*) begin
        ch_status_left[27:24]  = sample_rate_code;
        ch_status_right[27:24] = sample_rate_code;
    end

    reg spdif_clk = 0;
    // Generate SPDIF bit clock, divided by 2 from the main clock
    always @(posedge clk or posedge rst) begin
        if (rst) begin
            spdif_clk <= 0;
        end else begin
            spdif_clk <= ~spdif_clk; // Toggle SPDIF clock
        end
    end

    reg [7:0] ch_status_idx = 0;
    wire channel_status_bit_left  = ch_status_left[ch_status_idx];
    wire channel_status_bit_right = ch_status_right[ch_status_idx];

    // Subframe generation (without preamble)
    reg [27:0] subframe_data_left;
    reg [27:0] subframe_data_right;
    always @* begin
        subframe_data_left  = make_subframe(data_left, validity, 1'b0, channel_status_bit_left);
        subframe_data_right = make_subframe(data_right, validity, 1'b0, channel_status_bit_right);
    end

    // frame/block management
    reg [5:0] bit_idx = 0;
    reg       lr = 0;     // left/right
    reg [9:0] frame_count = 0; // block frame counter

    reg [27:0] shift_data;
    reg [3:0]  preamble_code;
    reg [3:0]  preamble_type;

    always @(negedge spdif_clk or posedge rst) begin
        if (rst) begin
            bit_idx <= 0;
            lr <= 0;
            frame_count <= 0;
        end else begin
            if (bit_idx == 31) begin
                bit_idx <= 0;
                lr <= ~lr;
                if (lr)
                    frame_count <= (frame_count == 191) ? 0 : frame_count + 1;
            end else begin
                bit_idx <= bit_idx + 1;
            end
        end
    end

    // BMC encoder state
    reg bmc_out = 0;
    reg bmc_phase = 0;

    always @(posedge clk or posedge rst) begin
        if (rst) begin
            bmc_out <= 0;
            bmc_phase <= 0;
            shift_data <= 0;
            preamble_type <= 4'b0000;
        end
        else begin
            if (bit_idx == 0) begin
                // new subframe
                if (lr == 0) begin
                    shift_data <= subframe_data_left;
                    // decide preamble
                    if (frame_count == 0)
                        preamble_type <= 4'b0001; // B
                    else
                        preamble_type <= 4'b0010; // M
                end
                else begin
                    shift_data <= subframe_data_right;
                    preamble_type <= 4'b0011; // W
                end
            end

            if (bit_idx < 4) begin
                // preamble bits override
                case (preamble_type)
                    4'b0001: // B preamble
                        bmc_out <= preamble_b(bit_idx);
                    4'b0010: // M preamble
                        bmc_out <= preamble_m(bit_idx);
                    4'b0011: // W preamble
                        bmc_out <= preamble_w(bit_idx);
                    default:
                        bmc_out <= 1;
                endcase
            end
            else begin
                // BMC encoding of bits 27..0
                if (bmc_phase == 0) begin
                    // always toggle start
                    bmc_out <= ~bmc_out;
                    bmc_phase <= 1;
                end else begin
                    if (shift_data[27])
                        bmc_out <= ~bmc_out; // extra transition for 1
                    else
                        bmc_out <= bmc_out; // 1 transition for 0
                    bmc_phase <= 0;

                    // shift down
                    shift_data <= {shift_data[26:0], 1'b0};
                end
            end
        end
    end

    always @(negedge clk)
        spdif_out <= bmc_out;

    // subframe creation function
    function [27:0] make_subframe;
        input [31:0] audio_data;
        input        validity;
        input        user;
        input        channel_status;
        reg   [27:0] temp;
        reg          parity;
        integer      i;
        begin
            temp = 28'b0;
            temp[27:4] = audio_data[23:0];
            temp[3] = validity;
            temp[2] = user;
            temp[1] = channel_status;

            parity = 0;
            for (i = 0; i < 27; i = i + 1)
                parity = parity ^ temp[i];
            temp[0] = parity;
            make_subframe = temp;
        end
    endfunction

    // preamble patterns for first 4 bits (in transitions)
    function preamble_b;
        input [5:0] idx;
        begin
            // e.g. B preamble code: 1110
            case (idx)
                0: preamble_b = 1'b1;
                1: preamble_b = 1'b1;
                2: preamble_b = 1'b1;
                3: preamble_b = 1'b0;
                default: preamble_b = 1'b0;
            endcase
        end
    endfunction
    function preamble_m;
        input [5:0] idx;
        begin
            case (idx)
                0: preamble_m = 1'b1;
                1: preamble_m = 1'b1;
                2: preamble_m = 1'b0;
                3: preamble_m = 1'b0;
                default: preamble_m = 1'b0;
            endcase
        end
    endfunction
    function preamble_w;
        input [5:0] idx;
        begin
            case (idx)
                0: preamble_w = 1'b1;
                1: preamble_w = 1'b0;
                2: preamble_w = 1'b0;
                3: preamble_w = 1'b0;
                default: preamble_w = 1'b0;
            endcase
        end
    endfunction

endmodule

verilog/spdif_transmit/spdif_transmit_tb.v
`timescale 1ns / 1ps

module spdif_transmit_tb;

    // Parameters
    localparam real CLK_FREQ     = 24_576_000;     // 24.576 MHz clock
    localparam real SPDIF_BAUD   = 12_288_000;     // 12.288 Mbps SPDIF rate for 192kHz
    localparam real CLK_PERIOD   = 1_000_000_000.0 / CLK_FREQ; // ~40.69 ns

    // DUT inputs
    reg         rst;
    reg         clk;
    reg  [31:0] data_left;
    reg  [31:0] data_right;
    reg         validity;
    reg  [3:0]  sample_rate_code;

    // DUT output
    wire        spdif_out;

    // Instantiate DUT
    spdif_transmit #(
        .SPDIF_BAUD(12_288_000),
        .CLK_FREQ(24_576_000)
    ) dut (
        .rst(rst),
        .clk(clk),
        .data_left(data_left),
        .data_right(data_right),
        .validity(validity),
        .sample_rate_code(sample_rate_code),
        .spdif_out(spdif_out)
    );

    // Clock generation (~40.69ns period)
    initial clk = 0;
    always #(CLK_PERIOD / 2) clk = ~clk;

    // Stimulus
    initial begin
        $display("Starting SPDIF transmitter test...");
        $dumpfile("spdif_transmit_tb.vcd");
        $dumpvars(0, spdif_transmit_tb);

        // Initial values
        rst = 1;
        data_left = 0;
        data_right = 0;
        validity = 0;
        sample_rate_code = 4'b1100; // 48kHz

        # (10 * CLK_PERIOD);
        rst = 0;

        // Stimulus: send several sample pairs
        repeat (3) begin
            data_left  = $random & 32'h00FFFFFF;
            data_right = $random & 32'h00FFFFFF;
            validity   = 0;
            #(256 * CLK_PERIOD); // Wait ~1 audio frame (2 subframes × 64 bits = 128 SPDIF bits)
        end

        $display("Simulation complete.");
        $finish;
    end

endmodule

verilog/spdif_transmit/spdif_transmit_tb.vcd
$date
	Thu Aug 07 20:34:35 2025
$end
$version
	Icarus Verilog
$end
$timescale
	1ps
$end
$scope module spdif_transmit_tb $end
$var wire 1 ! spdif_out $end
$var real 1 " CLK_FREQ $end
$var real 1 # CLK_PERIOD $end
$var real 1 $ SPDIF_BAUD $end
$var reg 1 % clk $end
$var reg 32 & data_left [31:0] $end
$var reg 32 ' data_right [31:0] $end
$var reg 1 ( rst $end
$var reg 4 ) sample_rate_code [3:0] $end
$var reg 1 * validity $end
$scope module dut $end
$var wire 1 % clk $end
$var wire 32 + data_left [31:0] $end
$var wire 32 , data_right [31:0] $end
$var wire 1 ( rst $end
$var wire 4 - sample_rate_code [3:0] $end
$var wire 1 * validity $end
$var wire 1 . channel_status_bit_right $end
$var wire 1 / channel_status_bit_left $end
$var parameter 32 0 CLK_DIV $end
$var parameter 32 1 CLK_FREQ $end
$var parameter 32 2 SPDIF_BAUD $end
$var reg 6 3 bit_idx [5:0] $end
$var reg 1 4 bmc_out $end
$var reg 1 5 bmc_phase $end
$var reg 8 6 ch_status_idx [7:0] $end
$var reg 192 7 ch_status_left [191:0] $end
$var reg 192 8 ch_status_right [191:0] $end
$var reg 10 9 frame_count [9:0] $end
$var reg 1 : lr $end
$var reg 4 ; preamble_type [3:0] $end
$var reg 28 < shift_data [27:0] $end
$var reg 1 = spdif_clk $end
$var reg 1 ! spdif_out $end
$var reg 28 > subframe_data_left [27:0] $end
$var reg 28 ? subframe_data_right [27:0] $end
$scope function make_subframe $end
$var reg 32 @ audio_data [31:0] $end
$var reg 1 A channel_status $end
$var reg 1 B parity $end
$var reg 28 C temp [27:0] $end
$var reg 1 D user $end
$var reg 1 E validity $end
$var integer 32 F i [31:0] $end
$upscope $end
$scope function preamble_b $end
$var reg 6 G idx [5:0] $end
$upscope $end
$scope function preamble_m $end
$var reg 6 H idx [5:0] $end
$upscope $end
$scope function preamble_w $end
$var reg 6 I idx [5:0] $end
$upscope $end
$upscope $end
$upscope $end
$enddefinitions $end
$comment Show the parameter values. $end
$dumpall
b101110111000000000000000 2
b1011101110000000000000000 1
b10 0
r12288000 $
r40.69010416666666 #
r24576000 "
$end
#0
$dumpvars
bx I
bx H
bx G
b11011 F
0E
0D
b0 C
0B
0A
b0 @
b0 ?
b0 >
0=
b0 <
b0 ;
0:
b0 9
b1100000000000000000000000000 8
b1100000000000000000000000000 7
b0 6
05
04
b0 3
0/
0.
b1100 -
b0 ,
b0 +
0*
b1100 )
1(
b0 '
b0 &
0%
0!
$end
#20345
1%
#40690
0%
#61035
1%
#81380
0%
#101725
1%
#122070
0%
#142415
1%
#162760
0%
#183105
1%
#203450
0%
#223795
1%
#244140
0%
#264485
1%
#284830
0%
#305175
1%
#325520
0%
#345865
1%
#366210
0%
#386555
1%
#406900
0%
#406901
b1000100101011110100000010001 ?
b1010100110101001001000001 >
1B
b11011 F
b1000100101011110100000010001 C
b100010010101111010000001 @
b100010010101111010000001 '
b100010010101111010000001 ,
b101010011010100100100 &
b101010011010100100100 +
0(
#427245
14
b1 ;
b1010100110101001001000001 <
1=
1%
#447590
1!
0%
#467935
b1 3
0=
b0 G
1%
#488280
0%
#508625
1=
b1 G
1%
#528970
0%
#549315
b10 3
0=
1%
#569660
0%
#590005
1=
b10 G
1%
#610350
0%
#630695
b11 3
0=
1%
#651040
0%
#671385
04
1=
b11 G
1%
#691730
0!
0%
#712075
b100 3
0=
1%
#732420
0%
#752765
15
14
1=
1%
#773110
1!
0%
#793455
b101 3
0=
b10101001101010010010000010 <
05
1%
#813800
0%
#834145
15
04
1=
1%
#854490
0!
0%
#874835
b110 3
0=
b101010011010100100100000100 <
05
1%
#895180
0%
#915525
15
14
1=
1%
#935870
1!
0%
#956215
b111 3
0=
b1010100110101001001000001000 <
05
1%
#976560
0%
#996905
15
04
1=
1%
#1017250
0!
0%
#1037595
b1000 3
0=
b101001101010010010000010000 <
05
14
1%
#1057940
1!
0%
#1078285
15
04
1=
1%
#1098630
0!
0%
#1118975
b1001 3
0=
b1010011010100100100000100000 <
05
1%
#1139320
0%
#1159665
15
14
1=
1%
#1180010
1!
0%
#1200355
b1010 3
0=
b100110101001001000001000000 <
05
04
1%
#1220700
0!
0%
#1241045
15
14
1=
1%
#1261390
1!
0%
#1281735
b1011 3
0=
b1001101010010010000010000000 <
05
1%
#1302080
0%
#1322425
15
04
1=
1%
#1342770
0!
0%
#1363115
b1100 3
0=
b11010100100100000100000000 <
05
14
1%
#1383460
1!
0%
#1403805
15
04
1=
1%
#1424150
0!
0%
#1444495
b1101 3
0=
b110101001001000001000000000 <
05
1%
#1464840
0%
#1485185
15
14
1=
1%
#1505530
1!
0%
#1525875
b1110 3
0=
b1101010010010000010000000000 <
05
1%
#1546220
0%
#1566565
15
04
1=
1%
#1586910
0!
0%
#1607255
b1111 3
0=
b1010100100100000100000000000 <
05
14
1%
#1627600
1!
0%
#1647945
15
04
1=
1%
#1668290
0!
0%
#1688635
b10000 3
0=
b101001001000001000000000000 <
05
14
1%
#1708980
1!
0%
#1729325
15
04
1=
1%
#1749670
0!
0%
#1770015
b10001 3
0=
b1010010010000010000000000000 <
05
1%
#1790360
0%
#1810705
15
14
1=
1%
#1831050
1!
0%
#1851395
b10010 3
0=
b100100100000100000000000000 <
05
04
1%
#1871740
0!
0%
#1892085
15
14
1=
1%
#1912430
1!
0%
#1932775
b10011 3
0=
b1001001000001000000000000000 <
05
1%
#1953120
0%
#1973465
15
04
1=
1%
#1993810
0!
0%
#2014155
b10100 3
0=
b10010000010000000000000000 <
05
14
1%
#2034500
1!
0%
#2054845
15
04
1=
1%
#2075190
0!
0%
#2095535
b10101 3
0=
b100100000100000000000000000 <
05
1%
#2115880
0%
#2136225
15
14
1=
1%
#2156570
1!
0%
#2176915
b10110 3
0=
b1001000001000000000000000000 <
05
1%
#2197260
0%
#2217605
15
04
1=
1%
#2237950
0!
0%
#2258295
b10111 3
0=
b10000010000000000000000000 <
05
14
1%
#2278640
1!
0%
#2298985
15
04
1=
1%
#2319330
0!
0%
#2339675
b11000 3
0=
b100000100000000000000000000 <
05
1%
#2360020
0%
#2380365
15
14
1=
1%
#2400710
1!
0%
#2421055
b11001 3
0=
b1000001000000000000000000000 <
05
1%
#2441400
0%
#2461745
15
04
1=
1%
#2482090
0!
0%
#2502435
b11010 3
0=
b10000000000000000000000 <
05
14
1%
#2522780
1!
0%
#2543125
15
04
1=
1%
#2563470
0!
0%
#2583815
b11011 3
0=
b100000000000000000000000 <
05
1%
#2604160
0%
#2624505
15
14
1=
1%
#2644850
1!
0%
#2665195
b11100 3
0=
b1000000000000000000000000 <
05
1%
#2685540
0%
#2705885
15
04
1=
1%
#2726230
0!
0%
#2746575
b11101 3
0=
b10000000000000000000000000 <
05
1%
#2766920
0%
#2787265
15
14
1=
1%
#2807610
1!
0%
#2827955
b11110 3
0=
b100000000000000000000000000 <
05
1%
#2848300
0%
#2868645
15
04
1=
1%
#2888990
0!
0%
#2909335
b11111 3
0=
b1000000000000000000000000000 <
05
1%
#2929680
0%
#2950025
15
14
1=
1%
#2970370
1!
0%
#2990715
1:
b0 3
0=
b0 <
05
04
1%
#3011060
0!
0%
#3031405
14
b11 ;
b1000100101011110100000010001 <
1=
b0 G
1%
#3051750
1!
0%
#3072095
b1 3
0=
b0 I
1%
#3092440
0%
#3112785
04
1=
b1 I
1%
#3133130
0!
0%
#3153475
b10 3
0=
1%
#3173820
0%
#3194165
1=
b10 I
1%
#3214510
0%
#3234855
b11 3
0=
1%
#3255200
0%
#3275545
1=
b11 I
1%
#3295890
0%
#3316235
b100 3
0=
1%
#3336580
0%
#3356925
15
14
1=
1%
#3377270
1!
0%
#3397615
b101 3
0=
b1001010111101000000100010 <
05
04
1%
#3417960
0!
0%
#3438305
15
14
1=
1%
#3458650
1!
0%
#3478995
b110 3
0=
b10010101111010000001000100 <
05
1%
#3499340
0%
#3519685
15
04
1=
1%
#3540030
0!
0%
#3560375
b111 3
0=
b100101011110100000010001000 <
05
1%
#3580720
0%
#3601065
15
14
1=
1%
#3621410
1!
0%
#3641755
b1000 3
0=
b1001010111101000000100010000 <
05
1%
#3662100
0%
#3682445
15
04
1=
1%
#3702790
0!
0%
#3723135
b1001 3
0=
b10101111010000001000100000 <
05
14
1%
#3743480
1!
0%
#3763825
15
04
1=
1%
#3784170
0!
0%
#3804515
b1010 3
0=
b101011110100000010001000000 <
05
1%
#3824860
0%
#3845205
15
14
1=
1%
#3865550
1!
0%
#3885895
b1011 3
0=
b1010111101000000100010000000 <
05
1%
#3906240
0%
#3926585
15
04
1=
1%
#3946930
0!
0%
#3967275
b1100 3
0=
b101111010000001000100000000 <
05
14
1%
#3987620
1!
0%
#4007965
15
04
1=
1%
#4028310
0!
0%
#4048655
b1101 3
0=
b1011110100000010001000000000 <
05
1%
#4069000
0%
#4089345
15
14
1=
1%
#4109690
1!
0%
#4130035
b1110 3
0=
b111101000000100010000000000 <
05
04
1%
#4150380
0!
0%
#4170725
15
14
1=
1%
#4191070
1!
0%
#4211415
b1111 3
0=
b1111010000001000100000000000 <
05
1%
#4231760
0%
#4252105
15
04
1=
1%
#4272450
0!
0%
#4292795
b10000 3
0=
b1110100000010001000000000000 <
05
14
1%
#4313140
1!
0%
#4333485
15
04
1=
1%
#4353830
0!
0%
#4374175
b10001 3
0=
b1101000000100010000000000000 <
05
14
1%
#4394520
1!
0%
#4414865
15
04
1=
1%
#4435210
0!
0%
#4455555
b10010 3
0=
b1010000001000100000000000000 <
05
14
1%
#4475900
1!
0%
#4496245
15
04
1=
1%
#4516590
0!
0%
#4536935
b10011 3
0=
b100000010001000000000000000 <
05
14
1%
#4557280
1!
0%
#4577625
15
04
1=
1%
#4597970
0!
0%
#4618315
b10100 3
0=
b1000000100010000000000000000 <
05
1%
#4638660
0%
#4659005
15
14
1=
1%
#4679350
1!
0%
#4699695
b10101 3
0=
b1000100000000000000000 <
05
04
1%
#4720040
0!
0%
#4740385
15
14
1=
1%
#4760730
1!
0%
#4781075
b10110 3
0=
b10001000000000000000000 <
05
1%
#4801420
0%
#4821765
15
04
1=
1%
#4842110
0!
0%
#4862455
b10111 3
0=
b100010000000000000000000 <
05
1%
#4882800
0%
#4903145
15
14
1=
1%
#4923490
1!
0%
#4943835
b11000 3
0=
b1000100000000000000000000 <
05
1%
#4964180
0%
#4984525
15
04
1=
1%
#5004870
0!
0%
#5025215
b11001 3
0=
b10001000000000000000000000 <
05
1%
#5045560
0%
#5065905
15
14
1=
1%
#5086250
1!
0%
#5106595
b11010 3
0=
b100010000000000000000000000 <
05
1%
#5126940
0%
#5147285
15
04
1=
1%
#5167630
0!
0%
#5187975
b11011 3
0=
b1000100000000000000000000000 <
05
1%
#5208320
0%
#5228665
15
14
1=
1%
#5249010
1!
0%
#5269355
b11100 3
0=
b1000000000000000000000000 <
05
04
1%
#5289700
0!
0%
#5310045
15
14
1=
1%
#5330390
1!
0%
#5350735
b11101 3
0=
b10000000000000000000000000 <
05
1%
#5371080
0%
#5391425
15
04
1=
1%
#5411770
0!
0%
#5432115
b11110 3
0=
b100000000000000000000000000 <
05
1%
#5452460
0%
#5472805
15
14
1=
1%
#5493150
1!
0%
#5513495
b11111 3
0=
b1000000000000000000000000000 <
05
1%
#5533840
0%
#5554185
15
04
1=
1%
#5574530
0!
0%
#5594875
b1 9
0:
b0 3
0=
b0 <
05
14
1%
#5615220
1!
0%
#5635565
b10 ;
b1010100110101001001000001 <
1=
b0 I
1%
#5655910
0%
#5676255
b1 3
0=
b0 H
1%
#5696600
0%
#5716945
1=
b1 H
1%
#5737290
0%
#5757635
b10 3
0=
1%
#5777980
0%
#5798325
04
1=
b10 H
1%
#5818670
0!
0%
#5839015
b11 3
0=
1%
#5859360
0%
#5879705
1=
b11 H
1%
#5900050
0%
#5920395
b100 3
0=
1%
#5940740
0%
#5961085
15
14
1=
1%
#5981430
1!
0%
#6001775
b101 3
0=
b10101001101010010010000010 <
05
1%
#6022120
0%
#6042465
15
04
1=
1%
#6062810
0!
0%
#6083155
b110 3
0=
b101010011010100100100000100 <
05
1%
#6103500
0%
#6123845
15
14
1=
1%
#6144190
1!
0%
#6164535
b111 3
0=
b1010100110101001001000001000 <
05
1%
#6184880
0%
#6205225
15
04
1=
1%
#6225570
0!
0%
#6245915
b1000 3
0=
b101001101010010010000010000 <
05
14
1%
#6266260
1!
0%
#6286605
15
04
1=
1%
#6306950
0!
0%
#6327295
b1001 3
0=
b1010011010100100100000100000 <
05
1%
#6347640
0%
#6367985
15
14
1=
1%
#6388330
1!
0%
#6408675
b1010 3
0=
b100110101001001000001000000 <
05
04
1%
#6429020
0!
0%
#6449365
15
14
1=
1%
#6469710
1!
0%
#6490055
b1011 3
0=
b1001101010010010000010000000 <
05
1%
#6510400
0%
#6530745
15
04
1=
1%
#6551090
0!
0%
#6571435
b1100 3
0=
b11010100100100000100000000 <
05
14
1%
#6591780
1!
0%
#6612125
15
04
1=
1%
#6632470
0!
0%
#6652815
b1101 3
0=
b110101001001000001000000000 <
05
1%
#6673160
0%
#6693505
15
14
1=
1%
#6713850
1!
0%
#6734195
b1110 3
0=
b1101010010010000010000000000 <
05
1%
#6754540
0%
#6774885
15
04
1=
1%
#6795230
0!
0%
#6815575
b1111 3
0=
b1010100100100000100000000000 <
05
14
1%
#6835920
1!
0%
#6856265
15
04
1=
1%
#6876610
0!
0%
#6896955
b10000 3
0=
b101001001000001000000000000 <
05
14
1%
#6917300
1!
0%
#6937645
15
04
1=
1%
#6957990
0!
0%
#6978335
b10001 3
0=
b1010010010000010000000000000 <
05
1%
#6998680
0%
#7019025
15
14
1=
1%
#7039370
1!
0%
#7059715
b10010 3
0=
b100100100000100000000000000 <
05
04
1%
#7080060
0!
0%
#7100405
15
14
1=
1%
#7120750
1!
0%
#7141095
b10011 3
0=
b1001001000001000000000000000 <
05
1%
#7161440
0%
#7181785
15
04
1=
1%
#7202130
0!
0%
#7222475
b10100 3
0=
b10010000010000000000000000 <
05
14
1%
#7242820
1!
0%
#7263165
15
04
1=
1%
#7283510
0!
0%
#7303855
b10101 3
0=
b100100000100000000000000000 <
05
1%
#7324200
0%
#7344545
15
14
1=
1%
#7364890
1!
0%
#7385235
b10110 3
0=
b1001000001000000000000000000 <
05
1%
#7405580
0%
#7425925
15
04
1=
1%
#7446270
0!
0%
#7466615
b10111 3
0=
b10000010000000000000000000 <
05
14
1%
#7486960
1!
0%
#7507305
15
04
1=
1%
#7527650
0!
0%
#7547995
b11000 3
0=
b100000100000000000000000000 <
05
1%
#7568340
0%
#7588685
15
14
1=
1%
#7609030
1!
0%
#7629375
b11001 3
0=
b1000001000000000000000000000 <
05
1%
#7649720
0%
#7670065
15
04
1=
1%
#7690410
0!
0%
#7710755
b11010 3
0=
b10000000000000000000000 <
05
14
1%
#7731100
1!
0%
#7751445
15
04
1=
1%
#7771790
0!
0%
#7792135
b11011 3
0=
b100000000000000000000000 <
05
1%
#7812480
0%
#7832825
15
14
1=
1%
#7853170
1!
0%
#7873515
b11100 3
0=
b1000000000000000000000000 <
05
1%
#7893860
0%
#7914205
15
04
1=
1%
#7934550
0!
0%
#7954895
b11101 3
0=
b10000000000000000000000000 <
05
1%
#7975240
0%
#7995585
15
14
1=
1%
#8015930
1!
0%
#8036275
b11110 3
0=
b100000000000000000000000000 <
05
1%
#8056620
0%
#8076965
15
04
1=
1%
#8097310
0!
0%
#8117655
b11111 3
0=
b1000000000000000000000000000 <
05
1%
#8138000
0%
#8158345
15
14
1=
1%
#8178690
1!
0%
#8199035
1:
b0 3
0=
b0 <
05
04
1%
#8219380
0!
0%
#8239725
14
b11 ;
b1000100101011110100000010001 <
1=
b0 H
1%
#8260070
1!
0%
#8280415
b1 3
0=
1%
#8300760
0%
#8321105
04
1=
b1 I
1%
#8341450
0!
0%
#8361795
b10 3
0=
1%
#8382140
0%
#8402485
1=
b10 I
1%
#8422830
0%
#8443175
b11 3
0=
1%
#8463520
0%
#8483865
1=
b11 I
1%
#8504210
0%
#8524555
b100 3
0=
1%
#8544900
0%
#8565245
15
14
1=
1%
#8585590
1!
0%
#8605935
b101 3
0=
b1001010111101000000100010 <
05
04
1%
#8626280
0!
0%
#8646625
15
14
1=
1%
#8666970
1!
0%
#8687315
b110 3
0=
b10010101111010000001000100 <
05
1%
#8707660
0%
#8728005
15
04
1=
1%
#8748350
0!
0%
#8768695
b111 3
0=
b100101011110100000010001000 <
05
1%
#8789040
0%
#8809385
15
14
1=
1%
#8829730
1!
0%
#8850075
b1000 3
0=
b1001010111101000000100010000 <
05
1%
#8870420
0%
#8890765
15
04
1=
1%
#8911110
0!
0%
#8931455
b1001 3
0=
b10101111010000001000100000 <
05
14
1%
#8951800
1!
0%
#8972145
15
04
1=
1%
#8992490
0!
0%
#9012835
b1010 3
0=
b101011110100000010001000000 <
05
1%
#9033180
0%
#9053525
15
14
1=
1%
#9073870
1!
0%
#9094215
b1011 3
0=
b1010111101000000100010000000 <
05
1%
#9114560
0%
#9134905
15
04
1=
1%
#9155250
0!
0%
#9175595
b1100 3
0=
b101111010000001000100000000 <
05
14
1%
#9195940
1!
0%
#9216285
15
04
1=
1%
#9236630
0!
0%
#9256975
b1101 3
0=
b1011110100000010001000000000 <
05
1%
#9277320
0%
#9297665
15
14
1=
1%
#9318010
1!
0%
#9338355
b1110 3
0=
b111101000000100010000000000 <
05
04
1%
#9358700
0!
0%
#9379045
15
14
1=
1%
#9399390
1!
0%
#9419735
b1111 3
0=
b1111010000001000100000000000 <
05
1%
#9440080
0%
#9460425
15
04
1=
1%
#9480770
0!
0%
#9501115
b10000 3
0=
b1110100000010001000000000000 <
05
14
1%
#9521460
1!
0%
#9541805
15
04
1=
1%
#9562150
0!
0%
#9582495
b10001 3
0=
b1101000000100010000000000000 <
05
14
1%
#9602840
1!
0%
#9623185
15
04
1=
1%
#9643530
0!
0%
#9663875
b10010 3
0=
b1010000001000100000000000000 <
05
14
1%
#9684220
1!
0%
#9704565
15
04
1=
1%
#9724910
0!
0%
#9745255
b10011 3
0=
b100000010001000000000000000 <
05
14
1%
#9765600
1!
0%
#9785945
15
04
1=
1%
#9806290
0!
0%
#9826635
b10100 3
0=
b1000000100010000000000000000 <
05
1%
#9846980
0%
#9867325
15
14
1=
1%
#9887670
1!
0%
#9908015
b10101 3
0=
b1000100000000000000000 <
05
04
1%
#9928360
0!
0%
#9948705
15
14
1=
1%
#9969050
1!
0%
#9989395
b10110 3
0=
b10001000000000000000000 <
05
1%
#10009740
0%
#10030085
15
04
1=
1%
#10050430
0!
0%
#10070775
b10111 3
0=
b100010000000000000000000 <
05
1%
#10091120
0%
#10111465
15
14
1=
1%
#10131810
1!
0%
#10152155
b11000 3
0=
b1000100000000000000000000 <
05
1%
#10172500
0%
#10192845
15
04
1=
1%
#10213190
0!
0%
#10233535
b11001 3
0=
b10001000000000000000000000 <
05
1%
#10253880
0%
#10274225
15
14
1=
1%
#10294570
1!
0%
#10314915
b11010 3
0=
b100010000000000000000000000 <
05
1%
#10335260
0%
#10355605
15
04
1=
1%
#10375950
0!
0%
#10396295
b11011 3
0=
b1000100000000000000000000000 <
05
1%
#10416640
0%
#10436985
15
14
1=
1%
#10457330
1!
0%
#10477675
b11100 3
0=
b1000000000000000000000000 <
05
04
1%
#10498020
0!
0%
#10518365
15
14
1=
1%
#10538710
1!
0%
#10559055
b11101 3
0=
b10000000000000000000000000 <
05
1%
#10579400
0%
#10599745
15
04
1=
1%
#10620090
0!
0%
#10640435
b11110 3
0=
b100000000000000000000000000 <
05
1%
#10660780
0%
#10681125
15
14
1=
1%
#10701470
1!
0%
#10721815
b11111 3
0=
b1000000000000000000000000000 <
05
1%
#10742160
0%
#10762505
15
04
1=
1%
#10782850
0!
0%
#10803195
b10 9
0:
b0 3
0=
b0 <
05
14
1%
#10823540
1!
0%
#10823568
b1111000001010110011000110001 ?
b1000010011010110000010010000 >
b11011 F
1B
b1111000001010110011000110001 C
b111100000101011001100011 @
b111100000101011001100011 '
b111100000101011001100011 ,
b100001001101011000001001 &
b100001001101011000001001 +
#10843885
b10 ;
b1000010011010110000010010000 <
1=
b0 I
1%
#10864230
0%
#10884575
b1 3
0=
1%
#10904920
0%
#10925265
1=
b1 H
1%
#10945610
0%
#10965955
b10 3
0=
1%
#10986300
0%
#11006645
04
1=
b10 H
1%
#11026990
0!
0%
#11047335
b11 3
0=
1%
#11067680
0%
#11088025
1=
b11 H
1%
#11108370
0%
#11128715
b100 3
0=
1%
#11149060
0%
#11169405
15
14
1=
1%
#11189750
1!
0%
#11210095
b101 3
0=
b100110101100000100100000 <
05
04
1%
#11230440
0!
0%
#11250785
15
14
1=
1%
#11271130
1!
0%
#11291475
b110 3
0=
b1001101011000001001000000 <
05
1%
#11311820
0%
#11332165
15
04
1=
1%
#11352510
0!
0%
#11372855
b111 3
0=
b10011010110000010010000000 <
05
1%
#11393200
0%
#11413545
15
14
1=
1%
#11433890
1!
0%
#11454235
b1000 3
0=
b100110101100000100100000000 <
05
1%
#11474580
0%
#11494925
15
04
1=
1%
#11515270
0!
0%
#11535615
b1001 3
0=
b1001101011000001001000000000 <
05
1%
#11555960
0%
#11576305
15
14
1=
1%
#11596650
1!
0%
#11616995
b1010 3
0=
b11010110000010010000000000 <
05
04
1%
#11637340
0!
0%
#11657685
15
14
1=
1%
#11678030
1!
0%
#11698375
b1011 3
0=
b110101100000100100000000000 <
05
1%
#11718720
0%
#11739065
15
04
1=
1%
#11759410
0!
0%
#11779755
b1100 3
0=
b1101011000001001000000000000 <
05
1%
#11800100
0%
#11820445
15
14
1=
1%
#11840790
1!
0%
#11861135
b1101 3
0=
b1010110000010010000000000000 <
05
04
1%
#11881480
0!
0%
#11901825
15
14
1=
1%
#11922170
1!
0%
#11942515
b1110 3
0=
b101100000100100000000000000 <
05
04
1%
#11962860
0!
0%
#11983205
15
14
1=
1%
#12003550
1!
0%
#12023895
b1111 3
0=
b1011000001001000000000000000 <
05
1%
#12044240
0%
#12064585
15
04
1=
1%
#12084930
0!
0%
#12105275
b10000 3
0=
b110000010010000000000000000 <
05
14
1%
#12125620
1!
0%
#12145965
15
04
1=
1%
#12166310
0!
0%
#12186655
b10001 3
0=
b1100000100100000000000000000 <
05
1%
#12207000
0%
#12227345
15
14
1=
1%
#12247690
1!
0%
#12268035
b10010 3
0=
b1000001001000000000000000000 <
05
04
1%
#12288380
0!
0%
#12308725
15
14
1=
1%
#12329070
1!
0%
#12349415
b10011 3
0=
b10010000000000000000000 <
05
04
1%
#12369760
0!
0%
#12390105
15
14
1=
1%
#12410450
1!
0%
#12430795
b10100 3
0=
b100100000000000000000000 <
05
1%
#12451140
0%
#12471485
15
04
1=
1%
#12491830
0!
0%
#12512175
b10101 3
0=
b1001000000000000000000000 <
05
1%
#12532520
0%
#12552865
15
14
1=
1%
#12573210
1!
0%
#12593555
b10110 3
0=
b10010000000000000000000000 <
05
1%
#12613900
0%
#12634245
15
04
1=
1%
#12654590
0!
0%
#12674935
b10111 3
0=
b100100000000000000000000000 <
05
1%
#12695280
0%
#12715625
15
14
1=
1%
#12735970
1!
0%
#12756315
b11000 3
0=
b1001000000000000000000000000 <
05
1%
#12776660
0%
#12797005
15
04
1=
1%
#12817350
0!
0%
#12837695
b11001 3
0=
b10000000000000000000000000 <
05
14
1%
#12858040
1!
0%
#12878385
15
04
1=
1%
#12898730
0!
0%
#12919075
b11010 3
0=
b100000000000000000000000000 <
05
1%
#12939420
0%
#12959765
15
14
1=
1%
#12980110
1!
0%
